Workbook

Sheet Transactions
A1: Lp | B1: Card | C1: Date | D1: Vehicle reg | E1: Location | F1: Product | G1: Category | H1: Qty (L/pcs) | I1: Unit net PLN (doc) | J1: Gross PLN | K1: VAT % | L1: VAT PLN | M1: Net PLN | N1: Check1: Net+VAT=Gross | O1: Check2: implied unit vs doc | P1: Check3: VAT = Net x rate
A2: 1 | B2: 000080 | C2: 27/05/26 | D2: BE9919 | E2: SUWALKI | F2: ON ACT. | G2: Diesel | H2: 300 | I2: 5.59 | J2: 1812.13 | K2: 8 | L2: 134.23 | M2: 1677.9 | N2: =IF(ABS(M2+L2-J2)<=0.01,"OK","CHECK") -> OK | O2: =IF(ABS(M2/H2-I2)<=0.005+0.01/H2,"OK","CHECK") -> OK | P2: =IF(ABS(L2-ROUND(M2*K2/100,2))<=0.02,"OK","CHECK") -> OK
A3: 2 | B3: 000122 | C3: 15/05/26 | D3: GH9909 | E3: SUWALKI | F3: ADBLUE | G3: AdBlue | H3: 20.02 | I3: 2.16 | J3: 53.11 | K3: 23 | L3: 9.93 | M3: 43.18 | N3: =IF(ABS(M3+L3-J3)<=0.01,"OK","CHECK") -> OK | O3: =IF(ABS(M3/H3-I3)<=0.005+0.01/H3,"OK","CHECK") -> OK | P3: =IF(ABS(L3-ROUND(M3*K3/100,2))<=0.02,"OK","CHECK") -> OK
A4: 3 | B4: 000122 | C4: 15/05/26 | D4: GH9909 | E4: SUWALKI | F4: ON ACT. | G4: Diesel | H4: 256.63 | I4: 5.82 | J4: 1612.52 | K4: 8 | L4: 119.45 | M4: 1493.07 | N4: =IF(ABS(M4+L4-J4)<=0.01,"OK","CHECK") -> OK | O4: =IF(ABS(M4/H4-I4)<=0.005+0.01/H4,"OK","CHECK") -> OK | P4: =IF(ABS(L4-ROUND(M4*K4/100,2))<=0.02,"OK","CHECK") -> OK
A5: 4 | B5: 000122 | C5: 26/05/26 | D5: GH9909 | E5: SUWALKI | F5: ADBLUE | G5: AdBlue | H5: 20.02 | I5: 2.16 | J5: 53.11 | K5: 23 | L5: 9.93 | M5: 43.18 | N5: =IF(ABS(M5+L5-J5)<=0.01,"OK","CHECK") -> OK | O5: =IF(ABS(M5/H5-I5)<=0.005+0.01/H5,"OK","CHECK") -> OK | P5: =IF(ABS(L5-ROUND(M5*K5/100,2))<=0.02,"OK","CHECK") -> OK
A6: 5 | B6: 000122 | C6: 28/05/26 | D6: GH9909 | E6: SUWALKI | F6: ADBLUE | G6: AdBlue | H6: 40.07 | I6: 2.16 | J6: 106.31 | K6: 23 | L6: 19.88 | M6: 86.43 | N6: =IF(ABS(M6+L6-J6)<=0.01,"OK","CHECK") -> OK | O6: =IF(ABS(M6/H6-I6)<=0.005+0.01/H6,"OK","CHECK") -> OK | P6: =IF(ABS(L6-ROUND(M6*K6/100,2))<=0.02,"OK","CHECK") -> OK
A7: 6 | B7: 000122 | C7: 28/05/26 | D7: GH9909 | E7: SUWALKI | F7: ON ACT. | G7: Diesel | H7: 110.12 | I7: 5.4 | J7: 642.1 | K7: 8 | L7: 47.56 | M7: 594.54 | N7: =IF(ABS(M7+L7-J7)<=0.01,"OK","CHECK") -> OK | O7: =IF(ABS(M7/H7-I7)<=0.005+0.01/H7,"OK","CHECK") -> OK | P7: =IF(ABS(L7-ROUND(M7*K7/100,2))<=0.02,"OK","CHECK") -> OK
A8: 7 | B8: 000130 | C8: 29/05/26 | D8: GR9 | E8: SUWALKI | F8: ON ACT. | G8: Diesel | H8: 400.04 | I8: 5.38 | J8: 2323.09 | K8: 8 | L8: 172.08 | M8: 2151.01 | N8: =IF(ABS(M8+L8-J8)<=0.01,"OK","CHECK") -> OK | O8: =IF(ABS(M8/H8-I8)<=0.005+0.01/H8,"OK","CHECK") -> OK | P8: =IF(ABS(L8-ROUND(M8*K8/100,2))<=0.02,"OK","CHECK") -> OK
A9: 8 | B9: 000171 | C9: 23/05/26 | D9: KP8998 | E9: SUWALKI | F9: ON ACT. | G9: Diesel | H9: 800.06 | I9: 5.85 | J9: 5055.64 | K9: 8 | L9: 374.49 | M9: 4681.15 | N9: =IF(ABS(M9+L9-J9)<=0.01,"OK","CHECK") -> OK | O9: =IF(ABS(M9/H9-I9)<=0.005+0.01/H9,"OK","CHECK") -> OK | P9: =IF(ABS(L9-ROUND(M9*K9/100,2))<=0.02,"OK","CHECK") -> OK
A10: 9 | B10: 000171 | C10: 28/05/26 | D10: KP8998 | E10: SUWALKI | F10: ON ACT. | G10: Diesel | H10: 568.72 | I10: 5.4 | J10: 3316.16 | K10: 8 | L10: 245.64 | M10: 3070.52 | N10: =IF(ABS(M10+L10-J10)<=0.01,"OK","CHECK") -> OK | O10: =IF(ABS(M10/H10-I10)<=0.005+0.01/H10,"OK","CHECK") -> OK | P10: =IF(ABS(L10-ROUND(M10*K10/100,2))<=0.02,"OK","CHECK") -> OK
A11: 10 | B11: 000189 | C11: 20/05/26 | D11: KS9339 | E11: RADZYMIN CIEMNE | F11: ON ACT. | G11: Diesel | H11: 550 | I11: 5.92 | J11: 3514.1 | K11: 8 | L11: 260.3 | M11: 3253.8 | N11: =IF(ABS(M11+L11-J11)<=0.01,"OK","CHECK") -> OK | O11: =IF(ABS(M11/H11-I11)<=0.005+0.01/H11,"OK","CHECK") -> OK | P11: =IF(ABS(L11-ROUND(M11*K11/100,2))<=0.02,"OK","CHECK") -> OK
A12: 11 | B12: 000247 | C12: 23/05/26 | D12: MV5097 | E12: SUWALKI | F12: ON ACT. | G12: Diesel | H12: 723.73 | I12: 5.85 | J12: 4573.3 | K12: 8 | L12: 338.76 | M12: 4234.54 | N12: =IF(ABS(M12+L12-J12)<=0.01,"OK","CHECK") -> OK | O12: =IF(ABS(M12/H12-I12)<=0.005+0.01/H12,"OK","CHECK") -> OK | P12: =IF(ABS(L12-ROUND(M12*K12/100,2))<=0.02,"OK","CHECK") -> OK
A13: 12 | B13: 000247 | C13: 23/05/26 | D13: MV5097 | E13: SUWALKI | F13: ON ACT. | G13: Diesel | H13: 366.56 | I13: 5.85 | J13: 2316.32 | K13: 8 | L13: 171.58 | M13: 2144.74 | N13: =IF(ABS(M13+L13-J13)<=0.01,"OK","CHECK") -> OK | O13: =IF(ABS(M13/H13-I13)<=0.005+0.01/H13,"OK","CHECK") -> OK | P13: =IF(ABS(L13-ROUND(M13*K13/100,2))<=0.02,"OK","CHECK") -> OK
... A47: 46 | B47: 000494 | C47: 30/05/26 | D47: ON989 | E47: SUWALKI | F47: ON ACT. | G47: Diesel | H47: 300.53 | I47: 5.38 | J47: 1745.23 | K47: 8 | L47: 129.28 | M47: 1615.95 | N47: =IF(ABS(M47+L47-J47)<=0.01,"OK","CHECK") -> OK | O47: =IF(ABS(M47/H47-I47)<=0.005+0.01/H47,"OK","CHECK") -> OK | P47: =IF(ABS(L47-ROUND(M47*K47/100,2))<=0.02,"OK","CHECK") -> OK

Sheet Card totals check
A1: Card | B1: Stated gross PLN | C1: Calc gross | D1: Diff | E1: Check
A2: 000080 | B2: 1812.13 | C2: =ROUND(SUMIF(Transactions!$B$2:$B$47,A2,Transactions!$J$2:$J$47),2) -> 1812.13 | D2: =C2-B2 -> 0 | E2: =IF(ABS(D2)<=0.01,"OK","CHECK") -> OK
A3: 000122 | B3: 2467.15 | C3: =ROUND(SUMIF(Transactions!$B$2:$B$47,A3,Transactions!$J$2:$J$47),2) -> 2467.15 | D3: =C3-B3 -> 0 | E3: =IF(ABS(D3)<=0.01,"OK","CHECK") -> OK
A4: 000130 | B4: 2323.09 | C4: =ROUND(SUMIF(Transactions!$B$2:$B$47,A4,Transactions!$J$2:$J$47),2) -> 2323.09 | D4: =C4-B4 -> 0 | E4: =IF(ABS(D4)<=0.01,"OK","CHECK") -> OK
A5: 000171 | B5: 8371.8 | C5: =ROUND(SUMIF(Transactions!$B$2:$B$47,A5,Transactions!$J$2:$J$47),2) -> 8371.8 | D5: =C5-B5 -> 0 | E5: =IF(ABS(D5)<=0.01,"OK","CHECK") -> OK
A6: 000189 | B6: 3514.1 | C6: =ROUND(SUMIF(Transactions!$B$2:$B$47,A6,Transactions!$J$2:$J$47),2) -> 3514.1 | D6: =C6-B6 -> 0 | E6: =IF(ABS(D6)<=0.01,"OK","CHECK") -> OK
A7: 000247 | B7: 6889.62 | C7: =ROUND(SUMIF(Transactions!$B$2:$B$47,A7,Transactions!$J$2:$J$47),2) -> 6889.62 | D7: =C7-B7 -> 0 | E7: =IF(ABS(D7)<=0.01,"OK","CHECK") -> OK
A8: 000254 | B8: 3895.73 | C8: =ROUND(SUMIF(Transactions!$B$2:$B$47,A8,Transactions!$J$2:$J$47),2) -> 3895.73 | D8: =C8-B8 -> 0 | E8: =IF(ABS(D8)<=0.01,"OK","CHECK") -> OK
A9: 000270 | B9: 4471.51 | C9: =ROUND(SUMIF(Transactions!$B$2:$B$47,A9,Transactions!$J$2:$J$47),2) -> 4471.51 | D9: =C9-B9 -> 0 | E9: =IF(ABS(D9)<=0.01,"OK","CHECK") -> OK
A10: 000288 | B10: 4233.85 | C10: =ROUND(SUMIF(Transactions!$B$2:$B$47,A10,Transactions!$J$2:$J$47),2) -> 4233.85 | D10: =C10-B10 -> 0 | E10: =IF(ABS(D10)<=0.01,"OK","CHECK") -> OK
A11: 000296 | B11: 1065.98 | C11: =ROUND(SUMIF(Transactions!$B$2:$B$47,A11,Transactions!$J$2:$J$47),2) -> 1065.98 | D11: =C11-B11 -> 0 | E11: =IF(ABS(D11)<=0.01,"OK","CHECK") -> OK
A12: 000312 | B12: 2867.8 | C12: =ROUND(SUMIF(Transactions!$B$2:$B$47,A12,Transactions!$J$2:$J$47),2) -> 2867.8 | D12: =C12-B12 -> 0 | E12: =IF(ABS(D12)<=0.01,"OK","CHECK") -> OK
A13: 000346 | B13: 6015.18 | C13: =ROUND(SUMIF(Transactions!$B$2:$B$47,A13,Transactions!$J$2:$J$47),2) -> 6015.18 | D13: =C13-B13 -> 0 | E13: =IF(ABS(D13)<=0.01,"OK","CHECK") -> OK
... A20: 000494 | B20: 1745.23 | C20: =ROUND(SUMIF(Transactions!$B$2:$B$47,A20,Transactions!$J$2:$J$47),2) -> 1745.23 | D20: =C20-B20 -> 0 | E20: =IF(ABS(D20)<=0.01,"OK","CHECK") -> OK
A21: TOTAL | B21: =SUM(B2:B20) -> 72215.36 | C21: =SUM(C2:C20) -> 72215.36 | D21: =C21-B21 -> 0 | E21: =IF(ABS(D21)<=0.01,"OK","CHECK") -> OK

Sheet Invoice totals check
A1: Check item | B1: Invoice states | C1: Calculated | D1: Diff | E1: Check
A2: Diesel (OLEJ NAPEDOWY) litres | B2: 11544.39 | C2: =ROUND(SUMIF(Transactions!$G$2:$G$47,"Diesel",Transactions!$H$2:$H$47),2) -> 11544.39 | D2: =C2-B2 -> 0 | E2: =IF(ABS(D2)<=0.01,"OK","CHECK") -> OK
A3: Diesel gross PLN | B3: 70768.51 | C3: =ROUND(SUMIF(Transactions!$G$2:$G$47,"Diesel",Transactions!$J$2:$J$47),2) -> 70768.51 | D3: =C3-B3 -> 0 | E3: =IF(ABS(D3)<=0.01,"OK","CHECK") -> OK
A4: Diesel net PLN | B4: 65526.42 | C4: =ROUND(SUMIF(Transactions!$G$2:$G$47,"Diesel",Transactions!$M$2:$M$47),2) -> 65526.42 | D4: =C4-B4 -> 0 | E4: =IF(ABS(D4)<=0.01,"OK","CHECK") -> OK
A5: AdBlue (AKCESORIA SAM.) litres | B5: 143.56 | C5: =ROUND(SUMIF(Transactions!$G$2:$G$47,"AdBlue",Transactions!$H$2:$H$47),2) -> 143.56 | D5: =C5-B5 -> 0 | E5: =IF(ABS(D5)<=0.01,"OK","CHECK") -> OK
A6: AdBlue gross PLN | B6: 380.87 | C6: =ROUND(SUMIF(Transactions!$G$2:$G$47,"AdBlue",Transactions!$J$2:$J$47),2) -> 380.87 | D6: =C6-B6 -> 0 | E6: =IF(ABS(D6)<=0.01,"OK","CHECK") -> OK
A7: Tolls (INNE PRODUKTY) item count | B7: 16 | C7: =SUMPRODUCT((LEFT(Transactions!$G$2:$G$47,4)="Toll")*Transactions!$H$2:$H$47) -> 16 | D7: =C7-B7 -> 0 | E7: =IF(ABS(D7)<=0.01,"OK","CHECK") -> OK
A8: Tolls gross PLN | B8: 1065.98 | C8: =ROUND(SUMPRODUCT((LEFT(Transactions!$G$2:$G$47,4)="Toll")*Transactions!$J$2:$J$47),2) -> 1065.98 | D8: =C8-B8 -> 0 | E8: =IF(ABS(D8)<=0.01,"OK","CHECK") -> OK
A9: VAT 8% base (net) PLN | B9: 65526.42 | C9: =ROUND(SUMIF(Transactions!$K$2:$K$47,8,Transactions!$M$2:$M$47),2) -> 65526.42 | D9: =C9-B9 -> 0 | E9: =IF(ABS(D9)<=0.01,"OK","CHECK") -> OK
A10: VAT 8% amount PLN | B10: 5242.09 | C10: =ROUND(SUMIF(Transactions!$K$2:$K$47,8,Transactions!$L$2:$L$47),2) -> 5242.09 | D10: =C10-B10 -> 0 | E10: =IF(ABS(D10)<=0.02,"OK","CHECK") -> OK
A11: VAT 23% base (net) PLN | B11: 1176.29 | C11: =ROUND(SUMIF(Transactions!$K$2:$K$47,23,Transactions!$M$2:$M$47),2) -> 1176.29 | D11: =C11-B11 -> 0 | E11: =IF(ABS(D11)<=0.01,"OK","CHECK") -> OK
A12: VAT 23% amount PLN | B12: 270.56 | C12: =ROUND(SUMIF(Transactions!$K$2:$K$47,23,Transactions!$L$2:$L$47),2) -> 270.56 | D12: =C12-B12 -> 0 | E12: =IF(ABS(D12)<=0.02,"OK","CHECK") -> OK
A13: TOTAL gross PLN (amount payable) | B13: 72215.36 | C13: =ROUND(SUM(Transactions!$J$2:$J$47),2) -> 72215.36 | D13: =C13-B13 -> 0 | E13: =IF(ABS(D13)<=0.01,"OK","CHECK") -> OK
A14: TOTAL VAT PLN | B14: 5512.65 | C14: =ROUND(SUM(Transactions!$L$2:$L$47),2) -> 5512.65 | D14: =C14-B14 -> 0 | E14: =IF(ABS(D14)<=0.02,"OK","CHECK") -> OK
A15: TOTAL net PLN | B15: 66702.71 | C15: =ROUND(SUM(Transactions!$M$2:$M$47),2) -> 66702.71 | D15: =C15-B15 -> 0 | E15: =IF(ABS(D15)<=0.01,"OK","CHECK") -> OK

Sheet Price analysis
A1: Diesel net unit price by date (PLN/L, rebated per invoice note)
A2: Date | B2: Litres | C2: Net PLN | D2: Avg net PLN/L
A3: 15/05/26 | B3: =SUMPRODUCT((Transactions!$C$2:$C$47=A3)*(Transactions!$G$2:$G$47="Diesel")*Transactions!$H$2:$H$47) -> 256.63 | C3: =SUMPRODUCT((Transactions!$C$2:$C$47=A3)*(Transactions!$G$2:$G$47="Diesel")*Transactions!$M$2:$M$47) -> 1493.07 | D3: =C3/B3 -> 5.817987
A4: 16/05/26 | B4: =SUMPRODUCT((Transactions!$C$2:$C$47=A4)*(Transactions!$G$2:$G$47="Diesel")*Transactions!$H$2:$H$47) -> 620 | C4: =SUMPRODUCT((Transactions!$C$2:$C$47=A4)*(Transactions!$G$2:$G$47="Diesel")*Transactions!$M$2:$M$47) -> 3607.16 | D4: =C4/B4 -> 5.818
A5: 17/05/26 | B5: =SUMPRODUCT((Transactions!$C$2:$C$47=A5)*(Transactions!$G$2:$G$47="Diesel")*Transactions!$H$2:$H$47) -> 1282.51 | C5: =SUMPRODUCT((Transactions!$C$2:$C$47=A5)*(Transactions!$G$2:$G$47="Diesel")*Transactions!$M$2:$M$47) -> 7461.65 | D5: =C5/B5 -> 5.8180053
A6: 18/05/26 | B6: =SUMPRODUCT((Transactions!$C$2:$C$47=A6)*(Transactions!$G$2:$G$47="Diesel")*Transactions!$H$2:$H$47) -> 350 | C6: =SUMPRODUCT((Transactions!$C$2:$C$47=A6)*(Transactions!$G$2:$G$47="Diesel")*Transactions!$M$2:$M$47) -> 2046.45 | D6: =C6/B6 -> 5.847
A7: 20/05/26 | B7: =SUMPRODUCT((Transactions!$C$2:$C$47=A7)*(Transactions!$G$2:$G$47="Diesel")*Transactions!$H$2:$H$47) -> 550 | C7: =SUMPRODUCT((Transactions!$C$2:$C$47=A7)*(Transactions!$G$2:$G$47="Diesel")*Transactions!$M$2:$M$47) -> 3253.8 | D7: =C7/B7 -> 5.916
A8: 21/05/26 | B8: =SUMPRODUCT((Transactions!$C$2:$C$47=A8)*(Transactions!$G$2:$G$47="Diesel")*Transactions!$H$2:$H$47) -> 664.86 | C8: =SUMPRODUCT((Transactions!$C$2:$C$47=A8)*(Transactions!$G$2:$G$47="Diesel")*Transactions!$M$2:$M$47) -> 3926.67 | D8: =C8/B8 -> 5.9060103
A9: 22/05/26 | B9: =SUMPRODUCT((Transactions!$C$2:$C$47=A9)*(Transactions!$G$2:$G$47="Diesel")*Transactions!$H$2:$H$47) -> 670.01 | C9: =SUMPRODUCT((Transactions!$C$2:$C$47=A9)*(Transactions!$G$2:$G$47="Diesel")*Transactions!$M$2:$M$47) -> 3920.23 | D9: =C9/B9 -> 5.8510022
A10: 23/05/26 | B10: =SUMPRODUCT((Transactions!$C$2:$C$47=A10)*(Transactions!$G$2:$G$47="Diesel")*Transactions!$H$2:$H$47) -> 2475.94 | C10: =SUMPRODUCT((Transactions!$C$2:$C$47=A10)*(Transactions!$G$2:$G$47="Diesel")*Transactions!$M$2:$M$47) -> 14486.71 | D10: =C10/B10 -> 5.850994
A11: 26/05/26 | B11: =SUMPRODUCT((Transactions!$C$2:$C$47=A11)*(Transactions!$G$2:$G$47="Diesel")*Transactions!$H$2:$H$47) -> 250.03 | C11: =SUMPRODUCT((Transactions!$C$2:$C$47=A11)*(Transactions!$G$2:$G$47="Diesel")*Transactions!$M$2:$M$47) -> 1437.67 | D11: =C11/B11 -> 5.74999
A12: 27/05/26 | B12: =SUMPRODUCT((Transactions!$C$2:$C$47=A12)*(Transactions!$G$2:$G$47="Diesel")*Transactions!$H$2:$H$47) -> 300 | C12: =SUMPRODUCT((Transactions!$C$2:$C$47=A12)*(Transactions!$G$2:$G$47="Diesel")*Transactions!$M$2:$M$47) -> 1677.9 | D12: =C12/B12 -> 5.593
A13: 28/05/26 | B13: =SUMPRODUCT((Transactions!$C$2:$C$47=A13)*(Transactions!$G$2:$G$47="Diesel")*Transactions!$H$2:$H$47) -> 1733.84 | C13: =SUMPRODUCT((Transactions!$C$2:$C$47=A13)*(Transactions!$G$2:$G$47="Diesel")*Transactions!$M$2:$M$47) -> 9361.01 | D13: =C13/B13 -> 5.3990045
A14: 29/05/26 | B14: =SUMPRODUCT((Transactions!$C$2:$C$47=A14)*(Transactions!$G$2:$G$47="Diesel")*Transactions!$H$2:$H$47) -> 400.04 | C14: =SUMPRODUCT((Transactions!$C$2:$C$47=A14)*(Transactions!$G$2:$G$47="Diesel")*Transactions!$M$2:$M$47) -> 2151.01 | D14: =C14/B14 -> 5.3769873
... A16: 31/05/26 | B16: =SUMPRODUCT((Transactions!$C$2:$C$47=A16)*(Transactions!$G$2:$G$47="Diesel")*Transactions!$H$2:$H$47) -> 1690 | C16: =SUMPRODUCT((Transactions!$C$2:$C$47=A16)*(Transactions!$G$2:$G$47="Diesel")*Transactions!$M$2:$M$47) -> 9087.14 | D16: =C16/B16 -> 5.3770059
A17: TOTAL | B17: =SUM(B3:B16) -> 11544.39 | C17: =SUM(C3:C16) -> 65526.42 | D17: =C17/B17 -> 5.6760401
