Workbook

Sheet Price summary
A1: MOEVE PRO BA72400000187538 - UAB Zaukos Transportas - PRICE OVERVIEW (Spain, May 2026)
A3: Diesel (STAR + Gasoleo A) by station | B3: Litres | C3: Final EUR incl VAT | D3: Eff. EUR/L incl VAT | E3: Eff. NET EUR/L excl VAT (10%)
A4: OIARTZUN I | B4: =SUMPRODUCT((Transactions!$D$2:$D$132=A4)*((Transactions!$E$2:$E$132="DIESEL STAR")+(Transactions!$E$2:$E$132="GASOLEO A"))*Transactions!$F$2:$F$132) -> 9387.23 | C4: =ROUND(SUMPRODUCT((Transactions!$D$2:$D$132=A4)*((Transactions!$E$2:$E$132="DIESEL STAR")+(Transactions!$E$2:$E$132="GASOLEO A"))*Transactions!$J$2:$J$132),2) -> 13753.01 | D4: =C4/B4 -> 1.4650765 | E4: =D4/1.1 -> 1.3318877
A5: OIARTZUN II | B5: =SUMPRODUCT((Transactions!$D$2:$D$132=A5)*((Transactions!$E$2:$E$132="DIESEL STAR")+(Transactions!$E$2:$E$132="GASOLEO A"))*Transactions!$F$2:$F$132) -> 10179.58 | C5: =ROUND(SUMPRODUCT((Transactions!$D$2:$D$132=A5)*((Transactions!$E$2:$E$132="DIESEL STAR")+(Transactions!$E$2:$E$132="GASOLEO A"))*Transactions!$J$2:$J$132),2) -> 15041.87 | D5: =C5/B5 -> 1.4776513 | E5: =D5/1.1 -> 1.3433194
A6: CANFRANC | B6: =SUMPRODUCT((Transactions!$D$2:$D$132=A6)*((Transactions!$E$2:$E$132="DIESEL STAR")+(Transactions!$E$2:$E$132="GASOLEO A"))*Transactions!$F$2:$F$132) -> 7537.84 | C6: =ROUND(SUMPRODUCT((Transactions!$D$2:$D$132=A6)*((Transactions!$E$2:$E$132="DIESEL STAR")+(Transactions!$E$2:$E$132="GASOLEO A"))*Transactions!$J$2:$J$132),2) -> 11873.23 | D6: =C6/B6 -> 1.5751502 | E6: =D6/1.1 -> 1.4319547
A7: LA JUNQUERA | B7: =SUMPRODUCT((Transactions!$D$2:$D$132=A7)*((Transactions!$E$2:$E$132="DIESEL STAR")+(Transactions!$E$2:$E$132="GASOLEO A"))*Transactions!$F$2:$F$132) -> 5905.52 | C7: =ROUND(SUMPRODUCT((Transactions!$D$2:$D$132=A7)*((Transactions!$E$2:$E$132="DIESEL STAR")+(Transactions!$E$2:$E$132="GASOLEO A"))*Transactions!$J$2:$J$132),2) -> 8835.57 | D7: =C7/B7 -> 1.4961544 | E7: =D7/1.1 -> 1.3601404
A8: EMPORDA | B8: =SUMPRODUCT((Transactions!$D$2:$D$132=A8)*((Transactions!$E$2:$E$132="DIESEL STAR")+(Transactions!$E$2:$E$132="GASOLEO A"))*Transactions!$F$2:$F$132) -> 2481.73 | C8: =ROUND(SUMPRODUCT((Transactions!$D$2:$D$132=A8)*((Transactions!$E$2:$E$132="DIESEL STAR")+(Transactions!$E$2:$E$132="GASOLEO A"))*Transactions!$J$2:$J$132),2) -> 3675.53 | D8: =C8/B8 -> 1.4810354 | E8: =D8/1.1 -> 1.3463958
A9: IBARBURU | B9: =SUMPRODUCT((Transactions!$D$2:$D$132=A9)*((Transactions!$E$2:$E$132="DIESEL STAR")+(Transactions!$E$2:$E$132="GASOLEO A"))*Transactions!$F$2:$F$132) -> 1533.1 | C9: =ROUND(SUMPRODUCT((Transactions!$D$2:$D$132=A9)*((Transactions!$E$2:$E$132="DIESEL STAR")+(Transactions!$E$2:$E$132="GASOLEO A"))*Transactions!$J$2:$J$132),2) -> 2141.62 | D9: =C9/B9 -> 1.3969213 | E9: =D9/1.1 -> 1.2699284
A10: VALLES NORTE | B10: =SUMPRODUCT((Transactions!$D$2:$D$132=A10)*((Transactions!$E$2:$E$132="DIESEL STAR")+(Transactions!$E$2:$E$132="GASOLEO A"))*Transactions!$F$2:$F$132) -> 943.14 | C10: =ROUND(SUMPRODUCT((Transactions!$D$2:$D$132=A10)*((Transactions!$E$2:$E$132="DIESEL STAR")+(Transactions!$E$2:$E$132="GASOLEO A"))*Transactions!$J$2:$J$132),2) -> 1313.99 | D10: =C10/B10 -> 1.3932078 | E10: =D10/1.1 -> 1.2665525
A11: ARAIA | B11: =SUMPRODUCT((Transactions!$D$2:$D$132=A11)*((Transactions!$E$2:$E$132="DIESEL STAR")+(Transactions!$E$2:$E$132="GASOLEO A"))*Transactions!$F$2:$F$132) -> 1142.64 | C11: =ROUND(SUMPRODUCT((Transactions!$D$2:$D$132=A11)*((Transactions!$E$2:$E$132="DIESEL STAR")+(Transactions!$E$2:$E$132="GASOLEO A"))*Transactions!$J$2:$J$132),2) -> 1678.48 | D11: =C11/B11 -> 1.4689491 | E11: =D11/1.1 -> 1.3354083
A12: LANZ | B12: =SUMPRODUCT((Transactions!$D$2:$D$132=A12)*((Transactions!$E$2:$E$132="DIESEL STAR")+(Transactions!$E$2:$E$132="GASOLEO A"))*Transactions!$F$2:$F$132) -> 712 | C12: =ROUND(SUMPRODUCT((Transactions!$D$2:$D$132=A12)*((Transactions!$E$2:$E$132="DIESEL STAR")+(Transactions!$E$2:$E$132="GASOLEO A"))*Transactions!$J$2:$J$132),2) -> 1036.67 | D12: =C12/B12 -> 1.4559972 | E12: =D12/1.1 -> 1.3236338
A13: VILAMALLA | B13: =SUMPRODUCT((Transactions!$D$2:$D$132=A13)*((Transactions!$E$2:$E$132="DIESEL STAR")+(Transactions!$E$2:$E$132="GASOLEO A"))*Transactions!$F$2:$F$132) -> 403.64 | C13: =ROUND(SUMPRODUCT((Transactions!$D$2:$D$132=A13)*((Transactions!$E$2:$E$132="DIESEL STAR")+(Transactions!$E$2:$E$132="GASOLEO A"))*Transactions!$J$2:$J$132),2) -> 588.51 | D13: =C13/B13 -> 1.4580071 | E13: =D13/1.1 -> 1.325461
A14: REQUENA II | B14: =SUMPRODUCT((Transactions!$D$2:$D$132=A14)*((Transactions!$E$2:$E$132="DIESEL STAR")+(Transactions!$E$2:$E$132="GASOLEO A"))*Transactions!$F$2:$F$132) -> 200.11 | C14: =ROUND(SUMPRODUCT((Transactions!$D$2:$D$132=A14)*((Transactions!$E$2:$E$132="DIESEL STAR")+(Transactions!$E$2:$E$132="GASOLEO A"))*Transactions!$J$2:$J$132),2) -> 337.38 | D14: =C14/B14 -> 1.6859727 | E14: =D14/1.1 -> 1.5327025
A15: TOTAL DIESEL (excl. April promo lines) | B15: =SUM(B4:B14) -> 40426.53 | C15: =SUM(C4:C14) -> 60275.86 | D15: =C15/B15 -> 1.4909976 | E15: =D15/1.1 -> 1.3554524
A16: April promo corrections (5 cts/L) | C16: -184.04
A17: ECOBLUE (AdBlue) all stations | B17: =SUMIF(Transactions!$E$2:$E$132,"ECOBLUE",Transactions!$F$2:$F$132) -> 1902.3 | C17: =ROUND(SUMIF(Transactions!$E$2:$E$132,"ECOBLUE",Transactions!$J$2:$J$132),2) -> 1209.36 | D17: =C17/B17 -> 0.63573569 | E17: =D17/1.21 -> 0.5254014
A19: Note: Moeve computes at 6 decimals and rounds displayed amounts; summed rounded lines differ from invoice headline figures by max 3 cents - not an error. All amounts include Spanish IVA (diesel 10%, AdBlue 21%); discounts (PRN) are off pump PVP. April promo lines (-184.04 EUR) are 5 cts/L corrections for 13-22 April fills billed in this statement.

Sheet Transactions
A1: Plate | B1: Date | C1: Time | D1: Station | E1: Concept | F1: Qty L | G1: PVP EUR/L (incl VAT) | H1: Operation EUR (calc qty x PVP) | I1: Discount EUR (PRN) | J1: Final EUR (incl VAT, doc) | K1: IVA % | L1: Paid cash EUR | M1: Eff. price EUR/L incl VAT | N1: Eff. net price EUR/L excl VAT | O1: Chk1: op-disc=final | P1: Chk2: vs doc op
A2: JEK861 | B2: 2026-05-30 | C2: 10:53 | D2: CANFRANC | E2: DIESEL STAR | F2: 680.22 | G2: 1.799 | H2: =ROUND(F2*G2,2) -> 1223.72 | I2: -206.107 | J2: 1017.61 | K2: 10 | M2: =IF(F2>0,J2/F2,"") -> 1.4960013 | N2: =IF(F2>0,J2/F2/(1+K2/100),"") -> 1.3600012 | O2: =IF(ABS(ROUND(F2*G2+I2,2)-J2)<=0.025,"OK","CHECK") -> OK | P2: =IF(F2=0,"promo line",IF(ABS(H2-F2*G2)<=0.011,"OK","CHECK")) -> OK
A3: JEK861 | B3: 2026-05-30 | C3: 10:53 | D3: CANFRANC | E3: ECOBLUE | F3: 29.52 | G3: 0.899 | H3: =ROUND(F3*G3,2) -> 26.54 | I3: 0 | J3: 26.54 | K3: 21 | M3: =IF(F3>0,J3/F3,"") -> 0.89905149 | N3: =IF(F3>0,J3/F3/(1+K3/100),"") -> 0.74301776 | O3: =IF(ABS(ROUND(F3*G3+I3,2)-J3)<=0.025,"OK","CHECK") -> OK | P3: =IF(F3=0,"promo line",IF(ABS(H3-F3*G3)<=0.011,"OK","CHECK")) -> OK
A4: JFB350 | B4: 2026-05-27 | C4: 13:10 | D4: OIARTZUN II | E4: DIESEL STAR | F4: 828.14 | G4: 1.738 | H4: =ROUND(F4*G4,2) -> 1439.31 | I4: -266.661 | J4: 1172.65 | K4: 10 | M4: =IF(F4>0,J4/F4,"") -> 1.4160045 | N4: =IF(F4>0,J4/F4/(1+K4/100),"") -> 1.2872769 | O4: =IF(ABS(ROUND(F4*G4+I4,2)-J4)<=0.025,"OK","CHECK") -> OK | P4: =IF(F4=0,"promo line",IF(ABS(H4-F4*G4)<=0.011,"OK","CHECK")) -> OK
A5: JFB350 | B5: 2026-05-27 | C5: 13:10 | D5: OIARTZUN II | E5: ECOBLUE | F5: 70.44 | G5: 0.995 | H5: =ROUND(F5*G5,2) -> 70.09 | I5: -34.093 | J5: 36 | K5: 21 | M5: =IF(F5>0,J5/F5,"") -> 0.51107325 | N5: =IF(F5>0,J5/F5/(1+K5/100),"") -> 0.42237459 | O5: =IF(ABS(ROUND(F5*G5+I5,2)-J5)<=0.025,"OK","CHECK") -> OK | P5: =IF(F5=0,"promo line",IF(ABS(H5-F5*G5)<=0.011,"OK","CHECK")) -> OK
A6: JGA310 | B6: 2026-05-26 | C6: 16:09 | D6: OIARTZUN II | E6: DIESEL STAR | F6: 740.22 | G6: 1.742 | H6: =ROUND(F6*G6,2) -> 1289.46 | I6: -233.169 | J6: 1056.29 | K6: 10 | M6: =IF(F6>0,J6/F6,"") -> 1.4269947 | N6: =IF(F6>0,J6/F6/(1+K6/100),"") -> 1.2972679 | O6: =IF(ABS(ROUND(F6*G6+I6,2)-J6)<=0.025,"OK","CHECK") -> OK | P6: =IF(F6=0,"promo line",IF(ABS(H6-F6*G6)<=0.011,"OK","CHECK")) -> OK
A7: JGH283 | B7: 2026-05-25 | C7: 17:04 | D7: OIARTZUN II | E7: DIESEL STAR | F7: 828.41 | G7: 1.742 | H7: =ROUND(F7*G7,2) -> 1443.09 | I7: -237.754 | J7: 1205.34 | K7: 10 | M7: =IF(F7>0,J7/F7,"") -> 1.4550042 | N7: =IF(F7>0,J7/F7/(1+K7/100),"") -> 1.3227311 | O7: =IF(ABS(ROUND(F7*G7+I7,2)-J7)<=0.025,"OK","CHECK") -> OK | P7: =IF(F7=0,"promo line",IF(ABS(H7-F7*G7)<=0.011,"OK","CHECK")) -> OK
A8: JGH283 | B8: 2026-05-25 | C8: 17:16 | D8: OIARTZUN II | E8: ECOBLUE | F8: 43.17 | G8: 0.995 | H8: =ROUND(F8*G8,2) -> 42.95 | I8: -20.894 | J8: 22.06 | K8: 21 | M8: =IF(F8>0,J8/F8,"") -> 0.51100301 | N8: =IF(F8>0,J8/F8/(1+K8/100),"") -> 0.42231654 | O8: =IF(ABS(ROUND(F8*G8+I8,2)-J8)<=0.025,"OK","CHECK") -> OK | P8: =IF(F8=0,"promo line",IF(ABS(H8-F8*G8)<=0.011,"OK","CHECK")) -> OK
A9: JHG876 | B9: 2026-05-25 | C9: 21:28 | D9: OIARTZUN I | E9: ECOBLUE | F9: 34.33 | G9: 0.995 | H9: =ROUND(F9*G9,2) -> 34.16 | I9: -16.616 | J9: 17.54 | K9: 21 | M9: =IF(F9>0,J9/F9,"") -> 0.51092339 | N9: =IF(F9>0,J9/F9/(1+K9/100),"") -> 0.42225074 | O9: =IF(ABS(ROUND(F9*G9+I9,2)-J9)<=0.025,"OK","CHECK") -> OK | P9: =IF(F9=0,"promo line",IF(ABS(H9-F9*G9)<=0.011,"OK","CHECK")) -> OK
A10: JHG876 | B10: 2026-05-25 | C10: 21:28 | D10: OIARTZUN I | E10: DIESEL STAR | F10: 769.1 | G10: 1.742 | H10: =ROUND(F10*G10,2) -> 1339.77 | I10: -220.732 | J10: 1119.04 | K10: 10 | M10: =IF(F10>0,J10/F10,"") -> 1.4549993 | N10: =IF(F10>0,J10/F10/(1+K10/100),"") -> 1.3227267 | O10: =IF(ABS(ROUND(F10*G10+I10,2)-J10)<=0.025,"OK","CHECK") -> OK | P10: =IF(F10=0,"promo line",IF(ABS(H10-F10*G10)<=0.011,"OK","CHECK")) -> OK
A11: JHJ165 | B11: 2026-04-13 | C11: 16:39 | D11: LA JUNQUERA | E11: Promo 5cts | F11: 0 | G11: 0.899 | H11: =ROUND(F11*G11,2) -> 0 | I11: -0.45 | J11: -0.45 | K11: 21 | M11: =IF(F11>0,J11/F11,"") | N11: =IF(F11>0,J11/F11/(1+K11/100),"") | O11: =IF(ABS(ROUND(F11*G11+I11,2)-J11)<=0.025,"OK","CHECK") -> OK | P11: =IF(F11=0,"promo line",IF(ABS(H11-F11*G11)<=0.011,"OK","CHECK")) -> promo line
A12: JHJ165 | B12: 2026-04-13 | C12: 16:39 | D12: LA JUNQUERA | E12: ECOBLUE | F12: 8.99 | G12: 0.899 | H12: =ROUND(F12*G12,2) -> 8.08 | I12: -4.037 | J12: 4.04 | K12: 21 | M12: =IF(F12>0,J12/F12,"") -> 0.44938821 | N12: =IF(F12>0,J12/F12/(1+K12/100),"") -> 0.37139521 | O12: =IF(ABS(ROUND(F12*G12+I12,2)-J12)<=0.025,"OK","CHECK") -> OK | P12: =IF(F12=0,"promo line",IF(ABS(H12-F12*G12)<=0.011,"OK","CHECK")) -> OK
A13: JHJ165 | B13: 2026-04-13 | C13: 16:39 | D13: LA JUNQUERA | E13: DIESEL STAR | F13: 823.14 | G13: 1.924 | H13: =ROUND(F13*G13,2) -> 1583.72 | I13: -229.656 | J13: 1354.06 | K13: 10 | M13: =IF(F13>0,J13/F13,"") -> 1.6449936 | N13: =IF(F13>0,J13/F13/(1+K13/100),"") -> 1.4954487 | O13: =IF(ABS(ROUND(F13*G13+I13,2)-J13)<=0.025,"OK","CHECK") -> OK | P13: =IF(F13=0,"promo line",IF(ABS(H13-F13*G13)<=0.011,"OK","CHECK")) -> OK
... A49: MIJ641 | B49: 2026-05-27 | C49: 19:49 | D49: CANFRANC | E49: DIESEL STAR | F49: 401.13 | G49: 1.799 | H49: =ROUND(F49*G49,2) -> 721.63 | I49: -98.678 | J49: 622.97 | K49: 10 | M49: =IF(F49>0,J49/F49,"") -> 1.5530377 | N49: =IF(F49>0,J49/F49/(1+K49/100),"") -> 1.4118524 | O49: =IF(ABS(ROUND(F49*G49+I49,2)-J49)<=0.025,"OK","CHECK") -> OK | P49: =IF(F49=0,"promo line",IF(ABS(H49-F49*G49)<=0.011,"OK","CHECK")) -> OK
A50: MIJ641 | B50: 2026-05-27 | C50: 20:29 | D50: CANFRANC | E50: DIESEL STAR | F50: 956.74 | G50: 1.799 | H50: =ROUND(F50*G50,2) -> 1721.18 | I50: -235.358 | J50: 1485.81 | K50: 10 | L50: 703.88 | M50: =IF(F50>0,J50/F50,"") -> 1.5529925 | N50: =IF(F50>0,J50/F50/(1+K50/100),"") -> 1.4118113 | O50: =IF(ABS(ROUND(F50*G50+I50,2)-J50)<=0.025,"OK","CHECK") -> OK | P50: =IF(F50=0,"promo line",IF(ABS(H50-F50*G50)<=0.011,"OK","CHECK")) -> OK
A51: MIJ641 | B51: 2026-05-27 | C51: 20:29 | D51: CANFRANC | E51: ECOBLUE | F51: 48.33 | G51: 0.899 | H51: =ROUND(F51*G51,2) -> 43.45 | I51: 0 | J51: 43.44 | K51: 21 | L51: 17.77 | M51: =IF(F51>0,J51/F51,"") -> 0.89882061 | N51: =IF(F51>0,J51/F51/(1+K51/100),"") -> 0.74282695 | O51: =IF(ABS(ROUND(F51*G51+I51,2)-J51)<=0.025,"OK","CHECK") -> OK | P51: =IF(F51=0,"promo line",IF(ABS(H51-F51*G51)<=0.011,"OK","CHECK")) -> OK
A52: MJD164 | B52: 2026-05-27 | C52: 16:48 | D52: CANFRANC | E52: DIESEL STAR | F52: 298.51 | G52: 1.799 | H52: =ROUND(F52*G52,2) -> 537.02 | I52: -73.433 | J52: 463.59 | K52: 10 | M52: =IF(F52>0,J52/F52,"") -> 1.5530133 | N52: =IF(F52>0,J52/F52/(1+K52/100),"") -> 1.4118303 | O52: =IF(ABS(ROUND(F52*G52+I52,2)-J52)<=0.025,"OK","CHECK") -> OK | P52: =IF(F52=0,"promo line",IF(ABS(H52-F52*G52)<=0.011,"OK","CHECK")) -> OK
A53: MJD164 | B53: 2026-05-27 | C53: 16:48 | D53: CANFRANC | E53: ECOBLUE | F53: 14.53 | G53: 0.899 | H53: =ROUND(F53*G53,2) -> 13.06 | I53: 0 | J53: 13.06 | K53: 21 | M53: =IF(F53>0,J53/F53,"") -> 0.89883001 | N53: =IF(F53>0,J53/F53/(1+K53/100),"") -> 0.74283472 | O53: =IF(ABS(ROUND(F53*G53+I53,2)-J53)<=0.025,"OK","CHECK") -> OK | P53: =IF(F53=0,"promo line",IF(ABS(H53-F53*G53)<=0.011,"OK","CHECK")) -> OK
A54: MJS272 | B54: 2026-05-19 | C54: 13:57 | D54: CANFRANC | E54: ECOBLUE | F54: 42.05 | G54: 0.899 | H54: =ROUND(F54*G54,2) -> 37.8 | I54: 0 | J54: 37.8 | K54: 21 | M54: =IF(F54>0,J54/F54,"") -> 0.89892985 | N54: =IF(F54>0,J54/F54/(1+K54/100),"") -> 0.74291723 | O54: =IF(ABS(ROUND(F54*G54+I54,2)-J54)<=0.025,"OK","CHECK") -> OK | P54: =IF(F54=0,"promo line",IF(ABS(H54-F54*G54)<=0.011,"OK","CHECK")) -> OK
A55: MJS272 | B55: 2026-05-19 | C55: 13:57 | D55: CANFRANC | E55: DIESEL STAR | F55: 722.62 | G55: 1.799 | H55: =ROUND(F55*G55,2) -> 1299.99 | I55: -115.619 | J55: 1184.38 | K55: 10 | M55: =IF(F55>0,J55/F55,"") -> 1.6390081 | N55: =IF(F55>0,J55/F55/(1+K55/100),"") -> 1.4900073 | O55: =IF(ABS(ROUND(F55*G55+I55,2)-J55)<=0.025,"OK","CHECK") -> OK | P55: =IF(F55=0,"promo line",IF(ABS(H55-F55*G55)<=0.011,"OK","CHECK")) -> OK
A56: MJS272 | B56: 2026-05-19 | C56: 14:33 | D56: CANFRANC | E56: DIESEL STAR | F56: 85.29 | G56: 1.799 | H56: =ROUND(F56*G56,2) -> 153.44 | I56: -13.646 | J56: 139.79 | K56: 10 | M56: =IF(F56>0,J56/F56,"") -> 1.6389964 | N56: =IF(F56>0,J56/F56/(1+K56/100),"") -> 1.4899967 | O56: =IF(ABS(ROUND(F56*G56+I56,2)-J56)<=0.025,"OK","CHECK") -> OK | P56: =IF(F56=0,"promo line",IF(ABS(H56-F56*G56)<=0.011,"OK","CHECK")) -> OK
A57: MPF855 | B57: 2026-05-21 | C57: 10:31 | D57: OIARTZUN I | E57: DIESEL STAR | F57: 400.14 | G57: 1.754 | H57: =ROUND(F57*G57,2) -> 701.85 | I57: -104.837 | J57: 597.01 | K57: 10 | M57: =IF(F57>0,J57/F57,"") -> 1.4920028 | N57: =IF(F57>0,J57/F57/(1+K57/100),"") -> 1.3563662 | O57: =IF(ABS(ROUND(F57*G57+I57,2)-J57)<=0.025,"OK","CHECK") -> OK | P57: =IF(F57=0,"promo line",IF(ABS(H57-F57*G57)<=0.011,"OK","CHECK")) -> OK
A58: MPF855 | B58: 2026-05-21 | C58: 10:31 | D58: OIARTZUN I | E58: ECOBLUE | F58: 24.04 | G58: 0.995 | H58: =ROUND(F58*G58,2) -> 23.92 | I58: -11.635 | J58: 12.28 | K58: 21 | M58: =IF(F58>0,J58/F58,"") -> 0.51081531 | N58: =IF(F58>0,J58/F58/(1+K58/100),"") -> 0.42216141 | O58: =IF(ABS(ROUND(F58*G58+I58,2)-J58)<=0.025,"OK","CHECK") -> OK | P58: =IF(F58=0,"promo line",IF(ABS(H58-F58*G58)<=0.011,"OK","CHECK")) -> OK
A59: MPI588 | B59: 2026-04-13 | C59: 15:29 | D59: LA JUNQUERA | E59: DIESEL STAR | F59: 550 | G59: 1.924 | H59: =ROUND(F59*G59,2) -> 1058.2 | I59: -153.45 | J59: 904.75 | K59: 10 | M59: =IF(F59>0,J59/F59,"") -> 1.645 | N59: =IF(F59>0,J59/F59/(1+K59/100),"") -> 1.4954545 | O59: =IF(ABS(ROUND(F59*G59+I59,2)-J59)<=0.025,"OK","CHECK") -> OK | P59: =IF(F59=0,"promo line",IF(ABS(H59-F59*G59)<=0.011,"OK","CHECK")) -> OK
A60: MPI588 | B60: 2026-04-13 | C60: 15:29 | D60: LA JUNQUERA | E60: Promo 5cts | F60: 0 | G60: 1.924 | H60: =ROUND(F60*G60,2) -> 0 | I60: -27.5 | J60: -27.5 | K60: 10 | M60: =IF(F60>0,J60/F60,"") | N60: =IF(F60>0,J60/F60/(1+K60/100),"") | O60: =IF(ABS(ROUND(F60*G60+I60,2)-J60)<=0.025,"OK","CHECK") -> OK | P60: =IF(F60=0,"promo line",IF(ABS(H60-F60*G60)<=0.011,"OK","CHECK")) -> promo line
A61: MSE954 | B61: 2026-05-23 | C61: 11:20 | D61: OIARTZUN I | E61: ECOBLUE | F61: 59.58 | G61: 0.995 | H61: =ROUND(F61*G61,2) -> 59.28 | I61: -28.837 | J61: 30.44 | K61: 21 | M61: =IF(F61>0,J61/F61,"") -> 0.5109097 | N61: =IF(F61>0,J61/F61/(1+K61/100),"") -> 0.42223942 | O61: =IF(ABS(ROUND(F61*G61+I61,2)-J61)<=0.025,"OK","CHECK") -> OK | P61: =IF(F61=0,"promo line",IF(ABS(H61-F61*G61)<=0.011,"OK","CHECK")) -> OK
A62: MSE954 | B62: 2026-05-23 | C62: 11:20 | D62: OIARTZUN I | E62: DIESEL STAR | F62: 728.3 | G62: 1.754 | H62: =ROUND(F62*G62,2) -> 1277.44 | I62: -217.762 | J62: 1059.68 | K62: 10 | M62: =IF(F62>0,J62/F62,"") -> 1.4550048 | N62: =IF(F62>0,J62/F62/(1+K62/100),"") -> 1.3227316 | O62: =IF(ABS(ROUND(F62*G62+I62,2)-J62)<=0.025,"OK","CHECK") -> OK | P62: =IF(F62=0,"promo line",IF(ABS(H62-F62*G62)<=0.011,"OK","CHECK")) -> OK
A63: MSE956 | B63: 2026-05-25 | C63: 09:09 | D63: OIARTZUN II | E63: DIESEL STAR | F63: 808.23 | G63: 1.742 | H63: =ROUND(F63*G63,2) -> 1407.94 | I63: -231.962 | J63: 1175.98 | K63: 10 | M63: =IF(F63>0,J63/F63,"") -> 1.4550066 | N63: =IF(F63>0,J63/F63/(1+K63/100),"") -> 1.3227333 | O63: =IF(ABS(ROUND(F63*G63+I63,2)-J63)<=0.025,"OK","CHECK") -> OK | P63: =IF(F63=0,"promo line",IF(ABS(H63-F63*G63)<=0.011,"OK","CHECK")) -> OK
... A132: NYA903 | B132: 2026-05-26 | C132: 08:34 | D132: CANFRANC | E132: DIESEL STAR | F132: 270 | G132: 1.799 | H132: =ROUND(F132*G132,2) -> 485.73 | I132: -63.45 | J132: 422.28 | K132: 10 | M132: =IF(F132>0,J132/F132,"") -> 1.564 | N132: =IF(F132>0,J132/F132/(1+K132/100),"") -> 1.4218182 | O132: =IF(ABS(ROUND(F132*G132+I132,2)-J132)<=0.025,"OK","CHECK") -> OK | P132: =IF(F132=0,"promo line",IF(ABS(H132-F132*G132)<=0.011,"OK","CHECK")) -> OK
A134: Tolerance ±0.025: invoice states amounts are computed internally at 6 decimals while PVP is displayed at 3 decimals, so recomputation from displayed figures drifts up to 2 cents (e.g. MIJ641 27-05 19:49).

Sheet Plate totals check
A1: Plate | B1: Stated total EUR | C1: Calc sum of finals | D1: Diff | E1: Check (±0.03 rounding)
A2: JEK861 | B2: 1044.15 | C2: =ROUND(SUMIF(Transactions!$A$2:$A$132,A2,Transactions!$J$2:$J$132),2) -> 1044.15 | D2: =C2-B2 -> 0 | E2: =IF(ABS(D2)<=0.03,"OK","CHECK") -> OK
A3: JFB350 | B3: 1208.65 | C3: =ROUND(SUMIF(Transactions!$A$2:$A$132,A3,Transactions!$J$2:$J$132),2) -> 1208.65 | D3: =C3-B3 -> 0 | E3: =IF(ABS(D3)<=0.03,"OK","CHECK") -> OK
A4: JGA310 | B4: 1056.29 | C4: =ROUND(SUMIF(Transactions!$A$2:$A$132,A4,Transactions!$J$2:$J$132),2) -> 1056.29 | D4: =C4-B4 -> 0 | E4: =IF(ABS(D4)<=0.03,"OK","CHECK") -> OK
A5: JGH283 | B5: 1227.39 | C5: =ROUND(SUMIF(Transactions!$A$2:$A$132,A5,Transactions!$J$2:$J$132),2) -> 1227.4 | D5: =C5-B5 -> 0.01 | E5: =IF(ABS(D5)<=0.03,"OK","CHECK") -> OK
A6: JHG876 | B6: 1136.58 | C6: =ROUND(SUMIF(Transactions!$A$2:$A$132,A6,Transactions!$J$2:$J$132),2) -> 1136.58 | D6: =C6-B6 -> 0 | E6: =IF(ABS(D6)<=0.03,"OK","CHECK") -> OK
A7: JHJ165 | B7: 2178.25 | C7: =ROUND(SUMIF(Transactions!$A$2:$A$132,A7,Transactions!$J$2:$J$132),2) -> 2178.24 | D7: =C7-B7 -> -0.01 | E7: =IF(ABS(D7)<=0.03,"OK","CHECK") -> OK
A8: JJB021 | B8: 833.09 | C8: =ROUND(SUMIF(Transactions!$A$2:$A$132,A8,Transactions!$J$2:$J$132),2) -> 833.08 | D8: =C8-B8 -> -0.01 | E8: =IF(ABS(D8)<=0.03,"OK","CHECK") -> OK
A9: JJC236 | B9: 1473.28 | C9: =ROUND(SUMIF(Transactions!$A$2:$A$132,A9,Transactions!$J$2:$J$132),2) -> 1473.28 | D9: =C9-B9 -> 0 | E9: =IF(ABS(D9)<=0.03,"OK","CHECK") -> OK
A10: JJH217 | B10: 1538.1 | C10: =ROUND(SUMIF(Transactions!$A$2:$A$132,A10,Transactions!$J$2:$J$132),2) -> 1538.11 | D10: =C10-B10 -> 0.01 | E10: =IF(ABS(D10)<=0.03,"OK","CHECK") -> OK
A11: JJH675 | B11: 812.78 | C11: =ROUND(SUMIF(Transactions!$A$2:$A$132,A11,Transactions!$J$2:$J$132),2) -> 812.78 | D11: =C11-B11 -> 0 | E11: =IF(ABS(D11)<=0.03,"OK","CHECK") -> OK
A12: JUG470 | B12: 1057.5 | C12: =ROUND(SUMIF(Transactions!$A$2:$A$132,A12,Transactions!$J$2:$J$132),2) -> 1057.5 | D12: =C12-B12 -> 0 | E12: =IF(ABS(D12)<=0.03,"OK","CHECK") -> OK
A13: JZP879 | B13: 859.3 | C13: =ROUND(SUMIF(Transactions!$A$2:$A$132,A13,Transactions!$J$2:$J$132),2) -> 859.3 | D13: =C13-B13 -> 0 | E13: =IF(ABS(D13)<=0.03,"OK","CHECK") -> OK
... A52: NYA903 | B52: 1738.53 | C52: =ROUND(SUMIF(Transactions!$A$2:$A$132,A52,Transactions!$J$2:$J$132),2) -> 1738.54 | D52: =C52-B52 -> 0.01 | E52: =IF(ABS(D52)<=0.03,"OK","CHECK") -> OK
A53: TOTAL | B53: =SUM(B2:B52) -> 61297.17 | C53: =SUM(C2:C52) -> 61297.18 | D53: =C53-B53 -> 0.01 | E53: =IF(ABS(D53)<=0.05,"OK","CHECK") -> OK

Sheet Invoice totals check
A1: Check item | B1: Invoice states | C1: Calculated from lines | D1: Diff | E1: Check | F1: Tolerance note
A2: DIESEL STAR litres | B2: 38880.25 | C2: =ROUND(SUMIF(Transactions!$E$2:$E$132,"DIESEL STAR",Transactions!$F$2:$F$132),2) -> 38880.25 | D2: =C2-B2 -> 0 | E2: =IF(ABS(D2)<=0.01,"OK","CHECK") -> OK
A3: DIESEL STAR gross before disc EUR | B3: 68786.96 | C3: =ROUND(SUMIF(Transactions!$E$2:$E$132,"DIESEL STAR",Transactions!$H$2:$H$132),2) -> 68786.93 | D3: =C3-B3 -> -0.03 | E3: =IF(ABS(D3)<=0.05,"OK","CHECK") -> OK | F3: 6-decimal rounding
A4: DIESEL STAR final EUR (concept summary 58,008.86) | B4: 58008.86 | C4: =ROUND(SUMIF(Transactions!$E$2:$E$132,"DIESEL STAR",Transactions!$J$2:$J$132),2) -> 58008.87 | D4: =C4-B4 -> 0.01 | E4: =IF(ABS(D4)<=0.05,"OK","CHECK") -> OK | F4: 6-decimal rounding
A5: GASOLEO A litres | B5: 1546.28 | C5: =ROUND(SUMIF(Transactions!$E$2:$E$132,"GASOLEO A",Transactions!$F$2:$F$132),2) -> 1546.28 | D5: =C5-B5 -> 0 | E5: =IF(ABS(D5)<=0.01,"OK","CHECK") -> OK
A6: GASOLEO A gross before disc EUR | B6: 2703.65 | C6: =ROUND(SUMIF(Transactions!$E$2:$E$132,"GASOLEO A",Transactions!$H$2:$H$132),2) -> 2703.65 | D6: =C6-B6 -> 0 | E6: =IF(ABS(D6)<=0.02,"OK","CHECK") -> OK
A7: GASOLEO A final EUR | B7: 2266.99 | C7: =ROUND(SUMIF(Transactions!$E$2:$E$132,"GASOLEO A",Transactions!$J$2:$J$132),2) -> 2266.99 | D7: =C7-B7 -> 0 | E7: =IF(ABS(D7)<=0.02,"OK","CHECK") -> OK
A8: ECOBLUE litres | B8: 1902.3 | C8: =ROUND(SUMIF(Transactions!$E$2:$E$132,"ECOBLUE",Transactions!$F$2:$F$132),2) -> 1902.3 | D8: =C8-B8 -> 0 | E8: =IF(ABS(D8)<=0.01,"OK","CHECK") -> OK
A9: ECOBLUE gross before disc EUR | B9: 1846.48 | C9: =ROUND(SUMIF(Transactions!$E$2:$E$132,"ECOBLUE",Transactions!$H$2:$H$132),2) -> 1846.48 | D9: =C9-B9 -> 0 | E9: =IF(ABS(D9)<=0.05,"OK","CHECK") -> OK | F9: 6-decimal rounding
A10: ECOBLUE final EUR (concept summary 1,209.33) | B10: 1209.33 | C10: =ROUND(SUMIF(Transactions!$E$2:$E$132,"ECOBLUE",Transactions!$J$2:$J$132),2) -> 1209.36 | D10: =C10-B10 -> 0.03 | E10: =IF(ABS(D10)<=0.05,"OK","CHECK") -> OK | F10: 6-decimal rounding
A11: Discount at 10% IVA EUR | B11: -11399.35 | C11: =ROUND(SUMIF(Transactions!$K$2:$K$132,10,Transactions!$I$2:$I$132),2) -> -11399.35 | D11: =C11-B11 -> 0 | E11: =IF(ABS(D11)<=0.02,"OK","CHECK") -> OK
A12: Discount at 21% IVA EUR | B12: -640.59 | C12: =ROUND(SUMIF(Transactions!$K$2:$K$132,21,Transactions!$I$2:$I$132),2) -> -640.58 | D12: =C12-B12 -> 0.01 | E12: =IF(ABS(D12)<=0.02,"OK","CHECK") -> OK
A13: Final at 10% IVA EUR (gross) | B13: 60091.26 | C13: =ROUND(SUMIF(Transactions!$K$2:$K$132,10,Transactions!$J$2:$J$132),2) -> 60091.26 | D13: =C13-B13 -> 0 | E13: =IF(ABS(D13)<=0.02,"OK","CHECK") -> OK
A14: implied base 10% | B14: 54628.42 | C14: =ROUND(C13/1.1,2) -> 54628.42 | D14: =C14-B14 -> 0 | E14: =IF(ABS(D14)<=0.05,"OK","CHECK") -> OK | F14: doc: 54,628.42 / cuota 5,462.84
A15: Final at 21% IVA EUR (gross) | B15: 1205.89 | C15: =ROUND(SUMIF(Transactions!$K$2:$K$132,21,Transactions!$J$2:$J$132),2) -> 1205.92 | D15: =C15-B15 -> 0.03 | E15: =IF(ABS(D15)<=0.05,"OK","CHECK") -> OK | F15: 6-decimal rounding
A16: implied base 21% | B16: 996.61 | C16: =ROUND(C15/1.21,2) -> 996.63 | D16: =C16-B16 -> 0.02 | E16: =IF(ABS(D16)<=0.05,"OK","CHECK") -> OK | F16: doc: 996.61 / cuota 209.28
A17: TOTAL DOCUMENT EUR | B17: 61297.15 | C17: =ROUND(SUM(Transactions!$J$2:$J$132),2) -> 61297.18 | D17: =C17-B17 -> 0.03 | E17: =IF(ABS(D17)<=0.05,"OK","CHECK") -> OK | F17: 6-decimal rounding
A18: Paid cash (al contado) EUR | B18: 721.65 | C18: =ROUND(SUM(Transactions!$L$2:$L$132),2) -> 721.65 | D18: =C18-B18 -> 0 | E18: =IF(ABS(D18)<=0.01,"OK","CHECK") -> OK | F18: MIJ641 27-05 fills
A19: Amount to settle by transfer EUR | B19: 60575.5 | C19: =C17-C18 -> 60575.53 | D19: =C19-B19 -> 0.03 | E19: =IF(ABS(D19)<=0.05,"OK","CHECK") -> OK | F19: due 30-06-2026
