Workbook

Sheet NET price summary
A1: NET PRICE OVERVIEW (excl. VAT, after E100 discount) - UAB Vestroidas, May 2026, Belgium
A3: Diesel by station | B3: Litres | C3: Net EUR | D3: Wtd avg net EUR/L | E3: Min net EUR/L | F3: Max net EUR/L | G3: Discount EUR/L
A4: BE94 Poperinge | B4: =SUMPRODUCT((Transactions!$E$2:$E$215=A4)*(Transactions!$F$2:$F$215="Diesel")*Transactions!$G$2:$G$215) -> 31202.35 | C4: =ROUND(SUMPRODUCT((Transactions!$E$2:$E$215=A4)*(Transactions!$F$2:$F$215="Diesel")*(Transactions!$M$2:$M$215-Transactions!$L$2:$L$215)),2) -> 49752.39 | D4: =C4/B4 -> 1.5945078 | E4: =_xlfn.MINIFS(Transactions!$K$2:$K$215,Transactions!$E$2:$E$215,A4,Transactions!$F$2:$F$215,"Diesel") -> 1.4942 | F4: =_xlfn.MAXIFS(Transactions!$K$2:$K$215,Transactions!$E$2:$E$215,A4,Transactions!$F$2:$F$215,"Diesel") -> 1.6653 | G4: 0.2300
A5: BE725 Longlier | B5: =SUMPRODUCT((Transactions!$E$2:$E$215=A5)*(Transactions!$F$2:$F$215="Diesel")*Transactions!$G$2:$G$215) -> 7907.9 | C5: =ROUND(SUMPRODUCT((Transactions!$E$2:$E$215=A5)*(Transactions!$F$2:$F$215="Diesel")*(Transactions!$M$2:$M$215-Transactions!$L$2:$L$215)),2) -> 13133.6 | D5: =C5/B5 -> 1.6608202 | E5: =_xlfn.MINIFS(Transactions!$K$2:$K$215,Transactions!$E$2:$E$215,A5,Transactions!$F$2:$F$215,"Diesel") -> 1.6173 | F5: =_xlfn.MAXIFS(Transactions!$K$2:$K$215,Transactions!$E$2:$E$215,A5,Transactions!$F$2:$F$215,"Diesel") -> 1.7066 | G5: 0.1800
A6: BE428 La Louviere | B6: =SUMPRODUCT((Transactions!$E$2:$E$215=A6)*(Transactions!$F$2:$F$215="Diesel")*Transactions!$G$2:$G$215) -> 4351.61 | C6: =ROUND(SUMPRODUCT((Transactions!$E$2:$E$215=A6)*(Transactions!$F$2:$F$215="Diesel")*(Transactions!$M$2:$M$215-Transactions!$L$2:$L$215)),2) -> 6513.76 | D6: =C6/B6 -> 1.4968621 | E6: =_xlfn.MINIFS(Transactions!$K$2:$K$215,Transactions!$E$2:$E$215,A6,Transactions!$F$2:$F$215,"Diesel") -> 1.4942 | F6: =_xlfn.MAXIFS(Transactions!$K$2:$K$215,Transactions!$E$2:$E$215,A6,Transactions!$F$2:$F$215,"Diesel") -> 1.6653 | G6: 0.2300
A7: BE92 Veurne | B7: =SUMPRODUCT((Transactions!$E$2:$E$215=A7)*(Transactions!$F$2:$F$215="Diesel")*Transactions!$G$2:$G$215) -> 2121.04 | C7: =ROUND(SUMPRODUCT((Transactions!$E$2:$E$215=A7)*(Transactions!$F$2:$F$215="Diesel")*(Transactions!$M$2:$M$215-Transactions!$L$2:$L$215)),2) -> 3505.51 | D7: =C7/B7 -> 1.6527317 | E7: =_xlfn.MINIFS(Transactions!$K$2:$K$215,Transactions!$E$2:$E$215,A7,Transactions!$F$2:$F$215,"Diesel") -> 1.5975 | F7: =_xlfn.MAXIFS(Transactions!$K$2:$K$215,Transactions!$E$2:$E$215,A7,Transactions!$F$2:$F$215,"Diesel") -> 1.6826 | G7: 0.1050
A8: BE9 Hoogstraten | B8: =SUMPRODUCT((Transactions!$E$2:$E$215=A8)*(Transactions!$F$2:$F$215="Diesel")*Transactions!$G$2:$G$215) -> 716.58 | C8: =ROUND(SUMPRODUCT((Transactions!$E$2:$E$215=A8)*(Transactions!$F$2:$F$215="Diesel")*(Transactions!$M$2:$M$215-Transactions!$L$2:$L$215)),2) -> 1225.75 | D8: =C8/B8 -> 1.7105557 | E8: =_xlfn.MINIFS(Transactions!$K$2:$K$215,Transactions!$E$2:$E$215,A8,Transactions!$F$2:$F$215,"Diesel") -> 1.7 | F8: =_xlfn.MAXIFS(Transactions!$K$2:$K$215,Transactions!$E$2:$E$215,A8,Transactions!$F$2:$F$215,"Diesel") -> 1.7454 | G8: 0.0800
A9: BE1042 Meer (orange) | B9: =SUMPRODUCT((Transactions!$E$2:$E$215=A9)*(Transactions!$F$2:$F$215="Diesel")*Transactions!$G$2:$G$215) -> 420 | C9: =ROUND(SUMPRODUCT((Transactions!$E$2:$E$215=A9)*(Transactions!$F$2:$F$215="Diesel")*(Transactions!$M$2:$M$215-Transactions!$L$2:$L$215)),2) -> 676.17 | D9: =C9/B9 -> 1.6099286 | E9: =_xlfn.MINIFS(Transactions!$K$2:$K$215,Transactions!$E$2:$E$215,A9,Transactions!$F$2:$F$215,"Diesel") -> 1.6099 | F9: =_xlfn.MAXIFS(Transactions!$K$2:$K$215,Transactions!$E$2:$E$215,A9,Transactions!$F$2:$F$215,"Diesel") -> 1.6099 | G9: 0.1930
A10: BE768 Meer-Hoogstraten | B10: =SUMPRODUCT((Transactions!$E$2:$E$215=A10)*(Transactions!$F$2:$F$215="Diesel")*Transactions!$G$2:$G$215) -> 72 | C10: =ROUND(SUMPRODUCT((Transactions!$E$2:$E$215=A10)*(Transactions!$F$2:$F$215="Diesel")*(Transactions!$M$2:$M$215-Transactions!$L$2:$L$215)),2) -> 114.9 | D10: =C10/B10 -> 1.5958333 | E10: =_xlfn.MINIFS(Transactions!$K$2:$K$215,Transactions!$E$2:$E$215,A10,Transactions!$F$2:$F$215,"Diesel") -> 1.5958 | F10: =_xlfn.MAXIFS(Transactions!$K$2:$K$215,Transactions!$E$2:$E$215,A10,Transactions!$F$2:$F$215,"Diesel") -> 1.5958 | G10: 0.1850
A11: TOTAL DIESEL | B11: =SUM(B4:B10) -> 46791.48 | C11: =SUM(C4:C10) -> 74922.08 | D11: =C11/B11 -> 1.6011906 | E11: =_xlfn.MINIFS(Transactions!$K$2:$K$215,Transactions!$F$2:$F$215,"Diesel") -> 1.4942 | F11: =_xlfn.MAXIFS(Transactions!$K$2:$K$215,Transactions!$F$2:$F$215,"Diesel") -> 1.7454
A13: AdBlue (all stations) | B13: =SUMIF(Transactions!$F$2:$F$215,"AdBlue",Transactions!$G$2:$G$215) -> 4529.81 | C13: =ROUND(SUMPRODUCT((Transactions!$F$2:$F$215="AdBlue")*(Transactions!$M$2:$M$215-Transactions!$L$2:$L$215)),2) -> 3094.88 | D13: =C13/B13 -> 0.68322512 | E13: =_xlfn.MINIFS(Transactions!$K$2:$K$215,Transactions!$F$2:$F$215,"AdBlue") -> 0.6354 | F13: =_xlfn.MAXIFS(Transactions!$K$2:$K$215,Transactions!$F$2:$F$215,"AdBlue") -> 1.0167 | G13: varies
A14: Parking (1 un.) | B14: 1 | C14: 30.3
A16: Diesel net price by half-month | B16: Litres | C16: Net EUR | D16: Wtd avg net EUR/L
A17: 01-15 May (BE98759) | B17: =SUMPRODUCT((Transactions!$A$2:$A$215="BE98759")*(Transactions!$F$2:$F$215="Diesel")*Transactions!$G$2:$G$215) -> 22336.88 | C17: =ROUND(SUMPRODUCT((Transactions!$A$2:$A$215="BE98759")*(Transactions!$F$2:$F$215="Diesel")*(Transactions!$M$2:$M$215-Transactions!$L$2:$L$215)),2) -> 36562.03 | D17: =C17/B17 -> 1.6368459
A18: 16-31 May (BE99954) | B18: =SUMPRODUCT((Transactions!$A$2:$A$215="BE99954")*(Transactions!$F$2:$F$215="Diesel")*Transactions!$G$2:$G$215) -> 24454.6 | C18: =ROUND(SUMPRODUCT((Transactions!$A$2:$A$215="BE99954")*(Transactions!$F$2:$F$215="Diesel")*(Transactions!$M$2:$M$215-Transactions!$L$2:$L$215)),2) -> 38360.05 | D18: =C18/B18 -> 1.5686231

Sheet Transactions
A1: Invoice | B1: Plate | C1: Date | D1: Time | E1: Station | F1: Product | G1: Qty (L/un) | H1: Gross price EUR (incl VAT) | I1: Discount EUR/L | J1: Discount total EUR | K1: Net price EUR/L (doc) | L1: VAT EUR | M1: Amount incl VAT EUR | N1: Chk1: discount=qty x rate | O1: Chk2: amount=qty x gross - disc | P1: Chk3: VAT=21/121 x amount | Q1: Chk4: net price
A2: BE98759 | B2: MTG433 | C2: 2026-05-04 | D2: 19:56 | E2: BE725 Longlier | F2: Diesel | G2: 427.62 | H2: 2.245 | I2: 0.18 | J2: 76.97 | K2: 1.7066 | L2: 153.25 | M2: 883.04 | N2: =IF(ABS(G2*I2-J2)<=0.011,"OK","CHECK") -> OK | O2: =IF(ABS(ROUND(G2*H2-J2,2)-M2)<=0.011,"OK","CHECK") -> OK | P2: =IF(ABS(ROUND(M2*21/121,2)-L2)<=0.011,"OK","CHECK") -> OK | Q2: =IF(ABS((M2-L2)/G2-K2)<=0.0006,"OK","CHECK") -> OK
A3: BE98759 | B3: MTG433 | C3: 2026-05-04 | D3: 20:04 | E3: BE725 Longlier | F3: AdBlue | G3: 79.53 | H3: 0.999 | I3: 0.23 | J3: 18.29 | K3: 0.6356 | L3: 10.61 | M3: 61.16 | N3: =IF(ABS(G3*I3-J3)<=0.011,"OK","CHECK") -> OK | O3: =IF(ABS(ROUND(G3*H3-J3,2)-M3)<=0.011,"OK","CHECK") -> OK | P3: =IF(ABS(ROUND(M3*21/121,2)-L3)<=0.011,"OK","CHECK") -> OK | Q3: =IF(ABS((M3-L3)/G3-K3)<=0.0006,"OK","CHECK") -> OK
A4: BE98759 | B4: MTG433 | C4: 2026-05-04 | D4: 20:07 | E4: BE725 Longlier | F4: Diesel | G4: 296.25 | H4: 2.245 | I4: 0.18 | J4: 53.33 | K4: 1.7066 | L4: 106.17 | M4: 611.75 | N4: =IF(ABS(G4*I4-J4)<=0.011,"OK","CHECK") -> OK | O4: =IF(ABS(ROUND(G4*H4-J4,2)-M4)<=0.011,"OK","CHECK") -> OK | P4: =IF(ABS(ROUND(M4*21/121,2)-L4)<=0.011,"OK","CHECK") -> OK | Q4: =IF(ABS((M4-L4)/G4-K4)<=0.0006,"OK","CHECK") -> OK
A5: BE98759 | B5: MTG433 | C5: 2026-05-06 | D5: 19:15 | E5: BE94 Poperinge | F5: Diesel | G5: 253.43 | H5: 2.245 | I5: 0.23 | J5: 58.29 | K5: 1.6653 | L5: 88.63 | M5: 510.66 | N5: =IF(ABS(G5*I5-J5)<=0.011,"OK","CHECK") -> OK | O5: =IF(ABS(ROUND(G5*H5-J5,2)-M5)<=0.011,"OK","CHECK") -> OK | P5: =IF(ABS(ROUND(M5*21/121,2)-L5)<=0.011,"OK","CHECK") -> OK | Q5: =IF(ABS((M5-L5)/G5-K5)<=0.0006,"OK","CHECK") -> OK
A6: BE98759 | B6: MTG433 | C6: 2026-05-06 | D6: 19:19 | E6: BE94 Poperinge | F6: Diesel | G6: 147.94 | H6: 2.245 | I6: 0.23 | J6: 34.03 | K6: 1.6653 | L6: 51.74 | M6: 298.1 | N6: =IF(ABS(G6*I6-J6)<=0.011,"OK","CHECK") -> OK | O6: =IF(ABS(ROUND(G6*H6-J6,2)-M6)<=0.011,"OK","CHECK") -> OK | P6: =IF(ABS(ROUND(M6*21/121,2)-L6)<=0.011,"OK","CHECK") -> OK | Q6: =IF(ABS((M6-L6)/G6-K6)<=0.0006,"OK","CHECK") -> OK
A7: BE98759 | B7: MTG433 | C7: 2026-05-09 | D7: 12:44 | E7: BE725 Longlier | F7: Diesel | G7: 260.6 | H7: 2.137 | I7: 0.18 | J7: 46.91 | K7: 1.6173 | L7: 88.51 | M7: 509.99 | N7: =IF(ABS(G7*I7-J7)<=0.011,"OK","CHECK") -> OK | O7: =IF(ABS(ROUND(G7*H7-J7,2)-M7)<=0.011,"OK","CHECK") -> OK | P7: =IF(ABS(ROUND(M7*21/121,2)-L7)<=0.011,"OK","CHECK") -> OK | Q7: =IF(ABS((M7-L7)/G7-K7)<=0.0006,"OK","CHECK") -> OK
A8: BE98759 | B8: MTG433 | C8: 2026-05-09 | D8: 12:49 | E8: BE725 Longlier | F8: AdBlue | G8: 54.99 | H8: 0.999 | I8: 0.23 | J8: 12.65 | K8: 0.6356 | L8: 7.34 | M8: 42.29 | N8: =IF(ABS(G8*I8-J8)<=0.011,"OK","CHECK") -> OK | O8: =IF(ABS(ROUND(G8*H8-J8,2)-M8)<=0.011,"OK","CHECK") -> OK | P8: =IF(ABS(ROUND(M8*21/121,2)-L8)<=0.011,"OK","CHECK") -> OK | Q8: =IF(ABS((M8-L8)/G8-K8)<=0.0006,"OK","CHECK") -> OK
A9: BE98759 | B9: MTG433 | C9: 2026-05-09 | D9: 14:20 | E9: BE725 Longlier | F9: Diesel | G9: 77.21 | H9: 2.137 | I9: 0.18 | J9: 13.9 | K9: 1.6174 | L9: 26.22 | M9: 151.1 | N9: =IF(ABS(G9*I9-J9)<=0.011,"OK","CHECK") -> OK | O9: =IF(ABS(ROUND(G9*H9-J9,2)-M9)<=0.011,"OK","CHECK") -> OK | P9: =IF(ABS(ROUND(M9*21/121,2)-L9)<=0.011,"OK","CHECK") -> OK | Q9: =IF(ABS((M9-L9)/G9-K9)<=0.0006,"OK","CHECK") -> OK
A10: BE98759 | B10: MTG433 | C10: 2026-05-09 | D10: 14:22 | E10: BE725 Longlier | F10: Diesel | G10: 57.87 | H10: 2.137 | I10: 0.18 | J10: 10.42 | K10: 1.6174 | L10: 19.65 | M10: 113.25 | N10: =IF(ABS(G10*I10-J10)<=0.011,"OK","CHECK") -> OK | O10: =IF(ABS(ROUND(G10*H10-J10,2)-M10)<=0.011,"OK","CHECK") -> OK | P10: =IF(ABS(ROUND(M10*21/121,2)-L10)<=0.011,"OK","CHECK") -> OK | Q10: =IF(ABS((M10-L10)/G10-K10)<=0.0006,"OK","CHECK") -> OK
A11: BE98759 | B11: MZD950 | C11: 2026-05-12 | D11: 11:30 | E11: BE94 Poperinge | F11: AdBlue | G11: 45.94 | H11: 1.0237 | I11: 0.22 | J11: 10.11 | K11: 0.6641 | L11: 6.41 | M11: 36.92 | N11: =IF(ABS(G11*I11-J11)<=0.011,"OK","CHECK") -> OK | O11: =IF(ABS(ROUND(G11*H11-J11,2)-M11)<=0.011,"OK","CHECK") -> OK | P11: =IF(ABS(ROUND(M11*21/121,2)-L11)<=0.011,"OK","CHECK") -> OK | Q11: =IF(ABS((M11-L11)/G11-K11)<=0.0006,"OK","CHECK") -> OK
A12: BE98759 | B12: MZD970 | C12: 2026-05-01 | D12: 00:03 | E12: BE94 Poperinge | F12: Diesel | G12: 435.11 | H12: 2.245 | I12: 0.23 | J12: 100.08 | K12: 1.6653 | L12: 152.16 | M12: 876.74 | N12: =IF(ABS(G12*I12-J12)<=0.011,"OK","CHECK") -> OK | O12: =IF(ABS(ROUND(G12*H12-J12,2)-M12)<=0.011,"OK","CHECK") -> OK | P12: =IF(ABS(ROUND(M12*21/121,2)-L12)<=0.011,"OK","CHECK") -> OK | Q12: =IF(ABS((M12-L12)/G12-K12)<=0.0006,"OK","CHECK") -> OK
A13: BE98759 | B13: MZD970 | C13: 2026-05-01 | D13: 00:11 | E13: BE94 Poperinge | F13: AdBlue | G13: 29 | H13: 1.0237 | I13: 0.22 | J13: 6.38 | K13: 0.6641 | L13: 4.05 | M13: 23.31 | N13: =IF(ABS(G13*I13-J13)<=0.011,"OK","CHECK") -> OK | O13: =IF(ABS(ROUND(G13*H13-J13,2)-M13)<=0.011,"OK","CHECK") -> OK | P13: =IF(ABS(ROUND(M13*21/121,2)-L13)<=0.011,"OK","CHECK") -> OK | Q13: =IF(ABS((M13-L13)/G13-K13)<=0.0006,"OK","CHECK") -> OK
... A215: BE99954 | B215: MZD958 | C215: 2026-05-22 | D215: 14:10 | E215: BE94 Poperinge | F215: AdBlue | G215: 34.06 | H215: 1.0237 | I215: 0.22 | J215: 7.49 | K215: 0.6644 | L215: 4.75 | M215: 27.38 | N215: =IF(ABS(G215*I215-J215)<=0.011,"OK","CHECK") -> OK | O215: =IF(ABS(ROUND(G215*H215-J215,2)-M215)<=0.011,"OK","CHECK") -> OK | P215: =IF(ABS(ROUND(M215*21/121,2)-L215)<=0.011,"OK","CHECK") -> OK | Q215: =IF(ABS((M215-L215)/G215-K215)<=0.0006,"OK","CHECK") -> OK

Sheet Invoice totals check
A1: Check item | B1: Invoice states | C1: Calculated | D1: Diff | E1: Check
A2: BE98759 Diesel litres | B2: 22336.88 | C2: =ROUND(SUMPRODUCT((Transactions!$A$2:$A$215="BE98759")*(Transactions!$F$2:$F$215="Diesel")*Transactions!$G$2:$G$215),2) -> 22336.88 | D2: =C2-B2 -> 0 | E2: =IF(ABS(D2)<=0.01,"OK","CHECK") -> OK
A3: BE98759 Diesel discount EUR | B3: 4589.11 | C3: =ROUND(SUMPRODUCT((Transactions!$A$2:$A$215="BE98759")*(Transactions!$F$2:$F$215="Diesel")*Transactions!$J$2:$J$215),2) -> 4589.11 | D3: =C3-B3 -> 0 | E3: =IF(ABS(D3)<=0.02,"OK","CHECK") -> OK
A4: BE98759 Diesel net (excl VAT) EUR | B4: 36562.02 | C4: =ROUND(SUMPRODUCT((Transactions!$A$2:$A$215="BE98759")*(Transactions!$F$2:$F$215="Diesel")*(Transactions!$M$2:$M$215-Transactions!$L$2:$L$215)),2) -> 36562.03 | D4: =C4-B4 -> 0.01 | E4: =IF(ABS(D4)<=0.05,"OK","CHECK") -> OK
A5: BE98759 AdBlue litres | B5: 2140.93 | C5: =ROUND(SUMPRODUCT((Transactions!$A$2:$A$215="BE98759")*(Transactions!$F$2:$F$215="AdBlue")*Transactions!$G$2:$G$215),2) -> 2140.93 | D5: =C5-B5 -> 0 | E5: =IF(ABS(D5)<=0.01,"OK","CHECK") -> OK
A6: BE98759 AdBlue gross EUR | B6: 1750 | C6: =ROUND(SUMPRODUCT((Transactions!$A$2:$A$215="BE98759")*(Transactions!$F$2:$F$215="AdBlue")*Transactions!$M$2:$M$215),2) -> 1750 | D6: =C6-B6 -> 0 | E6: =IF(ABS(D6)<=0.02,"OK","CHECK") -> OK
A7: BE98759 total discount EUR | B7: 5037.04 | C7: =ROUND(SUMIF(Transactions!$A$2:$A$215,"BE98759",Transactions!$J$2:$J$215),2) -> 5037.04 | D7: =C7-B7 -> 0 | E7: =IF(ABS(D7)<=0.02,"OK","CHECK") -> OK
A8: BE98759 total VAT EUR | B8: 7981.74 | C8: =ROUND(SUMIF(Transactions!$A$2:$A$215,"BE98759",Transactions!$L$2:$L$215),2) -> 7981.72 | D8: =C8-B8 -> -0.02 | E8: =IF(ABS(D8)<=0.05,"OK","CHECK") -> OK
A9: BE98759 TOTAL incl VAT EUR (payable) | B9: 45990.04 | C9: =ROUND(SUMIF(Transactions!$A$2:$A$215,"BE98759",Transactions!$M$2:$M$215),2) -> 45990.04 | D9: =C9-B9 -> 0 | E9: =IF(ABS(D9)<=0.02,"OK","CHECK") -> OK
A10: BE99954 Diesel litres | B10: 24454.6 | C10: =ROUND(SUMPRODUCT((Transactions!$A$2:$A$215="BE99954")*(Transactions!$F$2:$F$215="Diesel")*Transactions!$G$2:$G$215),2) -> 24454.6 | D10: =C10-B10 -> 0 | E10: =IF(ABS(D10)<=0.01,"OK","CHECK") -> OK
A11: BE99954 Diesel discount EUR | B11: 5386.14 | C11: =ROUND(SUMPRODUCT((Transactions!$A$2:$A$215="BE99954")*(Transactions!$F$2:$F$215="Diesel")*Transactions!$J$2:$J$215),2) -> 5386.14 | D11: =C11-B11 -> 0 | E11: =IF(ABS(D11)<=0.02,"OK","CHECK") -> OK
A12: BE99954 Diesel net (excl VAT) EUR | B12: 38360.05 | C12: =ROUND(SUMPRODUCT((Transactions!$A$2:$A$215="BE99954")*(Transactions!$F$2:$F$215="Diesel")*(Transactions!$M$2:$M$215-Transactions!$L$2:$L$215)),2) -> 38360.05 | D12: =C12-B12 -> 0 | E12: =IF(ABS(D12)<=0.05,"OK","CHECK") -> OK
A13: BE99954 AdBlue litres | B13: 2388.88 | C13: =ROUND(SUMPRODUCT((Transactions!$A$2:$A$215="BE99954")*(Transactions!$F$2:$F$215="AdBlue")*Transactions!$G$2:$G$215),2) -> 2388.88 | D13: =C13-B13 -> 0 | E13: =IF(ABS(D13)<=0.01,"OK","CHECK") -> OK
A14: BE99954 AdBlue gross EUR | B14: 1994.78 | C14: =ROUND(SUMPRODUCT((Transactions!$A$2:$A$215="BE99954")*(Transactions!$F$2:$F$215="AdBlue")*Transactions!$M$2:$M$215),2) -> 1994.78 | D14: =C14-B14 -> 0 | E14: =IF(ABS(D14)<=0.02,"OK","CHECK") -> OK
A15: BE99954 Parking gross EUR | B15: 36.66 | C15: =ROUND(SUMPRODUCT((Transactions!$A$2:$A$215="BE99954")*(Transactions!$F$2:$F$215="Parking")*Transactions!$M$2:$M$215),2) -> 36.66 | D15: =C15-B15 -> 0 | E15: =IF(ABS(D15)<=0.01,"OK","CHECK") -> OK
A16: BE99954 total discount EUR | B16: 6034.96 | C16: =ROUND(SUMIF(Transactions!$A$2:$A$215,"BE99954",Transactions!$J$2:$J$215),2) -> 6034.96 | D16: =C16-B16 -> 0 | E16: =IF(ABS(D16)<=0.02,"OK","CHECK") -> OK
A17: BE99954 total VAT EUR | B17: 8408.17 | C17: =ROUND(SUMIF(Transactions!$A$2:$A$215,"BE99954",Transactions!$L$2:$L$215),2) -> 8408.16 | D17: =C17-B17 -> -0.01 | E17: =IF(ABS(D17)<=0.05,"OK","CHECK") -> OK
A18: BE99954 TOTAL incl VAT EUR (payable) | B18: 48447.1 | C18: =ROUND(SUMIF(Transactions!$A$2:$A$215,"BE99954",Transactions!$M$2:$M$215),2) -> 48447.1 | D18: =C18-B18 -> 0 | E18: =IF(ABS(D18)<=0.02,"OK","CHECK") -> OK
A19: BOTH invoices payable EUR | B19: 94437.14 | C19: =ROUND(SUM(Transactions!$M$2:$M$215),2) -> 94437.14 | D19: =C19-B19 -> 0 | E19: =IF(ABS(D19)<=0.03,"OK","CHECK") -> OK

Sheet Card totals check
A1: Invoice | B1: Plate | C1: Stated card totals: discount | D1: VAT | E1: Gross | F1: Calc discount | G1: Calc VAT | H1: Calc gross | I1: Check
A2: BE98759 | B2: MTG433 | C2: 324.79 | D2: 552.12 | E2: 3181.34 | F2: =ROUND(SUMPRODUCT((Transactions!$A$2:$A$215=A2)*(Transactions!$B$2:$B$215=B2)*Transactions!$J$2:$J$215),2) -> 324.79 | G2: =ROUND(SUMPRODUCT((Transactions!$A$2:$A$215=A2)*(Transactions!$B$2:$B$215=B2)*Transactions!$L$2:$L$215),2) -> 552.12 | H2: =ROUND(SUMPRODUCT((Transactions!$A$2:$A$215=A2)*(Transactions!$B$2:$B$215=B2)*Transactions!$M$2:$M$215),2) -> 3181.34 | I2: =IF(AND(ABS(F2-C2)<=0.02,ABS(G2-D2)<=0.05,ABS(H2-E2)<=0.02),"OK","CHECK") -> OK
A3: BE98759 | B3: MZD950 | C3: 10.11 | D3: 6.41 | E3: 36.92 | F3: =ROUND(SUMPRODUCT((Transactions!$A$2:$A$215=A3)*(Transactions!$B$2:$B$215=B3)*Transactions!$J$2:$J$215),2) -> 10.11 | G3: =ROUND(SUMPRODUCT((Transactions!$A$2:$A$215=A3)*(Transactions!$B$2:$B$215=B3)*Transactions!$L$2:$L$215),2) -> 6.41 | H3: =ROUND(SUMPRODUCT((Transactions!$A$2:$A$215=A3)*(Transactions!$B$2:$B$215=B3)*Transactions!$M$2:$M$215),2) -> 36.92 | I3: =IF(AND(ABS(F3-C3)<=0.02,ABS(G3-D3)<=0.05,ABS(H3-E3)<=0.02),"OK","CHECK") -> OK
A4: BE98759 | B4: MZD970 | C4: 183.69 | D4: 400.02 | E4: 2304.85 | F4: =ROUND(SUMPRODUCT((Transactions!$A$2:$A$215=A4)*(Transactions!$B$2:$B$215=B4)*Transactions!$J$2:$J$215),2) -> 183.69 | G4: =ROUND(SUMPRODUCT((Transactions!$A$2:$A$215=A4)*(Transactions!$B$2:$B$215=B4)*Transactions!$L$2:$L$215),2) -> 400.02 | H4: =ROUND(SUMPRODUCT((Transactions!$A$2:$A$215=A4)*(Transactions!$B$2:$B$215=B4)*Transactions!$M$2:$M$215),2) -> 2304.85 | I4: =IF(AND(ABS(F4-C4)<=0.02,ABS(G4-D4)<=0.05,ABS(H4-E4)<=0.02),"OK","CHECK") -> OK
A5: BE98759 | B5: NGM038 | C5: 359.83 | D5: 587.1 | E5: 3382.87 | F5: =ROUND(SUMPRODUCT((Transactions!$A$2:$A$215=A5)*(Transactions!$B$2:$B$215=B5)*Transactions!$J$2:$J$215),2) -> 359.83 | G5: =ROUND(SUMPRODUCT((Transactions!$A$2:$A$215=A5)*(Transactions!$B$2:$B$215=B5)*Transactions!$L$2:$L$215),2) -> 587.1 | H5: =ROUND(SUMPRODUCT((Transactions!$A$2:$A$215=A5)*(Transactions!$B$2:$B$215=B5)*Transactions!$M$2:$M$215),2) -> 3382.87 | I5: =IF(AND(ABS(F5-C5)<=0.02,ABS(G5-D5)<=0.05,ABS(H5-E5)<=0.02),"OK","CHECK") -> OK
A6: BE98759 | B6: NGM043 | C6: 175.13 | D6: 310.77 | E6: 1790.61 | F6: =ROUND(SUMPRODUCT((Transactions!$A$2:$A$215=A6)*(Transactions!$B$2:$B$215=B6)*Transactions!$J$2:$J$215),2) -> 175.13 | G6: =ROUND(SUMPRODUCT((Transactions!$A$2:$A$215=A6)*(Transactions!$B$2:$B$215=B6)*Transactions!$L$2:$L$215),2) -> 310.77 | H6: =ROUND(SUMPRODUCT((Transactions!$A$2:$A$215=A6)*(Transactions!$B$2:$B$215=B6)*Transactions!$M$2:$M$215),2) -> 1790.61 | I6: =IF(AND(ABS(F6-C6)<=0.02,ABS(G6-D6)<=0.05,ABS(H6-E6)<=0.02),"OK","CHECK") -> OK
A7: BE98759 | B7: NGM601 | C7: 44 | D7: 208.26 | E7: 1199.96 | F7: =ROUND(SUMPRODUCT((Transactions!$A$2:$A$215=A7)*(Transactions!$B$2:$B$215=B7)*Transactions!$J$2:$J$215),2) -> 44 | G7: =ROUND(SUMPRODUCT((Transactions!$A$2:$A$215=A7)*(Transactions!$B$2:$B$215=B7)*Transactions!$L$2:$L$215),2) -> 208.26 | H7: =ROUND(SUMPRODUCT((Transactions!$A$2:$A$215=A7)*(Transactions!$B$2:$B$215=B7)*Transactions!$M$2:$M$215),2) -> 1199.96 | I7: =IF(AND(ABS(F7-C7)<=0.02,ABS(G7-D7)<=0.05,ABS(H7-E7)<=0.02),"OK","CHECK") -> OK
A8: BE98759 | B8: NGM594 | C8: 132.86 | D8: 243 | E8: 1400.14 | F8: =ROUND(SUMPRODUCT((Transactions!$A$2:$A$215=A8)*(Transactions!$B$2:$B$215=B8)*Transactions!$J$2:$J$215),2) -> 132.86 | G8: =ROUND(SUMPRODUCT((Transactions!$A$2:$A$215=A8)*(Transactions!$B$2:$B$215=B8)*Transactions!$L$2:$L$215),2) -> 243 | H8: =ROUND(SUMPRODUCT((Transactions!$A$2:$A$215=A8)*(Transactions!$B$2:$B$215=B8)*Transactions!$M$2:$M$215),2) -> 1400.14 | I8: =IF(AND(ABS(F8-C8)<=0.02,ABS(G8-D8)<=0.05,ABS(H8-E8)<=0.02),"OK","CHECK") -> OK
A9: BE98759 | B9: NGM884 | C9: 354.02 | D9: 494.65 | E9: 2850.14 | F9: =ROUND(SUMPRODUCT((Transactions!$A$2:$A$215=A9)*(Transactions!$B$2:$B$215=B9)*Transactions!$J$2:$J$215),2) -> 354.02 | G9: =ROUND(SUMPRODUCT((Transactions!$A$2:$A$215=A9)*(Transactions!$B$2:$B$215=B9)*Transactions!$L$2:$L$215),2) -> 494.65 | H9: =ROUND(SUMPRODUCT((Transactions!$A$2:$A$215=A9)*(Transactions!$B$2:$B$215=B9)*Transactions!$M$2:$M$215),2) -> 2850.14 | I9: =IF(AND(ABS(F9-C9)<=0.02,ABS(G9-D9)<=0.05,ABS(H9-E9)<=0.02),"OK","CHECK") -> OK
A10: BE98759 | B10: NGM883 | C10: 59.19 | D10: 92.1 | E10: 530.7 | F10: =ROUND(SUMPRODUCT((Transactions!$A$2:$A$215=A10)*(Transactions!$B$2:$B$215=B10)*Transactions!$J$2:$J$215),2) -> 59.19 | G10: =ROUND(SUMPRODUCT((Transactions!$A$2:$A$215=A10)*(Transactions!$B$2:$B$215=B10)*Transactions!$L$2:$L$215),2) -> 92.1 | H10: =ROUND(SUMPRODUCT((Transactions!$A$2:$A$215=A10)*(Transactions!$B$2:$B$215=B10)*Transactions!$M$2:$M$215),2) -> 530.7 | I10: =IF(AND(ABS(F10-C10)<=0.02,ABS(G10-D10)<=0.05,ABS(H10-E10)<=0.02),"OK","CHECK") -> OK
A11: BE98759 | B11: NEP680 | C11: 25.73 | D11: 52.91 | E11: 304.9 | F11: =ROUND(SUMPRODUCT((Transactions!$A$2:$A$215=A11)*(Transactions!$B$2:$B$215=B11)*Transactions!$J$2:$J$215),2) -> 25.73 | G11: =ROUND(SUMPRODUCT((Transactions!$A$2:$A$215=A11)*(Transactions!$B$2:$B$215=B11)*Transactions!$L$2:$L$215),2) -> 52.91 | H11: =ROUND(SUMPRODUCT((Transactions!$A$2:$A$215=A11)*(Transactions!$B$2:$B$215=B11)*Transactions!$M$2:$M$215),2) -> 304.9 | I11: =IF(AND(ABS(F11-C11)<=0.02,ABS(G11-D11)<=0.05,ABS(H11-E11)<=0.02),"OK","CHECK") -> OK
A12: BE98759 | B12: MYI227 | C12: 378.73 | D12: 634.57 | E12: 3656.33 | F12: =ROUND(SUMPRODUCT((Transactions!$A$2:$A$215=A12)*(Transactions!$B$2:$B$215=B12)*Transactions!$J$2:$J$215),2) -> 378.73 | G12: =ROUND(SUMPRODUCT((Transactions!$A$2:$A$215=A12)*(Transactions!$B$2:$B$215=B12)*Transactions!$L$2:$L$215),2) -> 634.57 | H12: =ROUND(SUMPRODUCT((Transactions!$A$2:$A$215=A12)*(Transactions!$B$2:$B$215=B12)*Transactions!$M$2:$M$215),2) -> 3656.33 | I12: =IF(AND(ABS(F12-C12)<=0.02,ABS(G12-D12)<=0.05,ABS(H12-E12)<=0.02),"OK","CHECK") -> OK
A13: BE98759 | B13: MYI228 | C13: 6.6 | D13: 4.18 | E13: 24.11 | F13: =ROUND(SUMPRODUCT((Transactions!$A$2:$A$215=A13)*(Transactions!$B$2:$B$215=B13)*Transactions!$J$2:$J$215),2) -> 6.6 | G13: =ROUND(SUMPRODUCT((Transactions!$A$2:$A$215=A13)*(Transactions!$B$2:$B$215=B13)*Transactions!$L$2:$L$215),2) -> 4.18 | H13: =ROUND(SUMPRODUCT((Transactions!$A$2:$A$215=A13)*(Transactions!$B$2:$B$215=B13)*Transactions!$M$2:$M$215),2) -> 24.11 | I13: =IF(AND(ABS(F13-C13)<=0.02,ABS(G13-D13)<=0.05,ABS(H13-E13)<=0.02),"OK","CHECK") -> OK
... A54: BE99954 | B54: MZD958 | C54: 7.49 | D54: 4.75 | E54: 27.38 | F54: =ROUND(SUMPRODUCT((Transactions!$A$2:$A$215=A54)*(Transactions!$B$2:$B$215=B54)*Transactions!$J$2:$J$215),2) -> 7.49 | G54: =ROUND(SUMPRODUCT((Transactions!$A$2:$A$215=A54)*(Transactions!$B$2:$B$215=B54)*Transactions!$L$2:$L$215),2) -> 4.75 | H54: =ROUND(SUMPRODUCT((Transactions!$A$2:$A$215=A54)*(Transactions!$B$2:$B$215=B54)*Transactions!$M$2:$M$215),2) -> 27.38 | I54: =IF(AND(ABS(F54-C54)<=0.02,ABS(G54-D54)<=0.05,ABS(H54-E54)<=0.02),"OK","CHECK") -> OK
