Workbook

Sheet Transactions
A1: Card | B1: Date | C1: Time | D1: Receipt | E1: Plate | F1: Product | G1: Location | H1: Volume L | I1: Location price EUR/L | J1: Discount EUR/L | K1: Net price EUR/L (doc) | L1: Net amount EUR (doc) | M1: Eff. price used | N1: Check1: price math | O1: Calc amount | P1: Diff | Q1: Check2: amount
A2: 108019237 | B2: 27-05-26 | C2: 11:42 | D2: 110795 | E2: NCK 218 | F2: Diesel | G2: Romac Houdeng | H2: 456 | I2: 1.5944 | L2: 727.05 | M2: =IF(K2<>"",K2,I2) -> 1.5944 | N2: =IF(K2="","n/a (no discount)",IF(ABS(I2-J2-K2)<=0.0001,"OK","CHECK")) -> n/a (no discount) | O2: =ROUND(M2*H2,2) -> 727.05 | P2: =O2-L2 -> 0 | Q2: =IF(ABS(P2)<=0.011,"OK","CHECK") -> OK
A3: 108019237 | B3: 27-05-26 | C3: 11:50 | D3: 110817 | E3: NCK 218 | F3: Diesel | G3: Romac Houdeng | H3: 51 | I3: 1.5944 | L3: 81.32 | M3: =IF(K3<>"",K3,I3) -> 1.5944 | N3: =IF(K3="","n/a (no discount)",IF(ABS(I3-J3-K3)<=0.0001,"OK","CHECK")) -> n/a (no discount) | O3: =ROUND(M3*H3,2) -> 81.31 | P3: =O3-L3 -> -0.01 | Q3: =IF(ABS(P3)<=0.011,"OK","CHECK") -> OK
A4: 108019237 | B4: 27-05-26 | C4: 11:54 | D4: 110829 | E4: NCK 218 | F4: Diesel | G4: Romac Houdeng | H4: 24 | I4: 1.5944 | L4: 38.27 | M4: =IF(K4<>"",K4,I4) -> 1.5944 | N4: =IF(K4="","n/a (no discount)",IF(ABS(I4-J4-K4)<=0.0001,"OK","CHECK")) -> n/a (no discount) | O4: =ROUND(M4*H4,2) -> 38.27 | P4: =O4-L4 -> 0 | Q4: =IF(ABS(P4)<=0.011,"OK","CHECK") -> OK
A5: 108019237 | B5: 29-05-26 | C5: 15:10 | D5: 117360 | E5: NCK 218 | F5: Diesel | G5: Tfc Dcb Energy Hub Meer | H5: 271 | I5: 1.6843 | J5: 0.205 | K5: 1.4793 | L5: 400.9 | M5: =IF(K5<>"",K5,I5) -> 1.4793 | N5: =IF(K5="","n/a (no discount)",IF(ABS(I5-J5-K5)<=0.0001,"OK","CHECK")) -> OK | O5: =ROUND(M5*H5,2) -> 400.89 | P5: =O5-L5 -> -0.01 | Q5: =IF(ABS(P5)<=0.011,"OK","CHECK") -> OK
A6: 108019237 | B6: 29-05-26 | C6: 15:19 | D6: 117410 | E6: NCK 218 | F6: Diesel | G6: Tfc Dcb Energy Hub Meer | H6: 26 | I6: 1.6843 | J6: 0.205 | K6: 1.4793 | L6: 38.47 | M6: =IF(K6<>"",K6,I6) -> 1.4793 | N6: =IF(K6="","n/a (no discount)",IF(ABS(I6-J6-K6)<=0.0001,"OK","CHECK")) -> OK | O6: =ROUND(M6*H6,2) -> 38.46 | P6: =O6-L6 -> -0.01 | Q6: =IF(ABS(P6)<=0.011,"OK","CHECK") -> OK
A7: 108019237 | B7: 29-05-26 | C7: 15:21 | D7: 117425 | E7: NCK 218 | F7: Diesel | G7: Tfc Dcb Energy Hub Meer | H7: 137.01 | I7: 1.6843 | J7: 0.205 | K7: 1.4793 | L7: 202.68 | M7: =IF(K7<>"",K7,I7) -> 1.4793 | N7: =IF(K7="","n/a (no discount)",IF(ABS(I7-J7-K7)<=0.0001,"OK","CHECK")) -> OK | O7: =ROUND(M7*H7,2) -> 202.68 | P7: =O7-L7 -> 0 | Q7: =IF(ABS(P7)<=0.011,"OK","CHECK") -> OK
A8: 108019237 | B8: 27-05-26 | C8: 11:47 | D8: 110809 | E8: NCK 218 | F8: AdBlue | G8: Romac Houdeng | H8: 30 | I8: 0.675 | L8: 20.25 | M8: =IF(K8<>"",K8,I8) -> 0.675 | N8: =IF(K8="","n/a (no discount)",IF(ABS(I8-J8-K8)<=0.0001,"OK","CHECK")) -> n/a (no discount) | O8: =ROUND(M8*H8,2) -> 20.25 | P8: =O8-L8 -> 0 | Q8: =IF(ABS(P8)<=0.011,"OK","CHECK") -> OK
A9: 108019237 | B9: 29-05-26 | C9: 15:15 | D9: 117389 | E9: NCK 218 | F9: AdBlue | G9: Tfc Dcb Energy Hub Meer | H9: 48.11 | I9: 0.6 | J9: 0 | K9: 0.6 | L9: 28.87 | M9: =IF(K9<>"",K9,I9) -> 0.6 | N9: =IF(K9="","n/a (no discount)",IF(ABS(I9-J9-K9)<=0.0001,"OK","CHECK")) -> OK | O9: =ROUND(M9*H9,2) -> 28.87 | P9: =O9-L9 -> 0 | Q9: =IF(ABS(P9)<=0.011,"OK","CHECK") -> OK
A10: 145993502 | B10: 18-05-26 | C10: 13:38 | D10: 84860 | E10: MSZ552 | F10: Diesel | G10: Tfc Dcb Energy Hub Meer | H10: 445 | I10: 1.7488 | J10: 0.205 | K10: 1.5438 | L10: 687 | M10: =IF(K10<>"",K10,I10) -> 1.5438 | N10: =IF(K10="","n/a (no discount)",IF(ABS(I10-J10-K10)<=0.0001,"OK","CHECK")) -> OK | O10: =ROUND(M10*H10,2) -> 686.99 | P10: =O10-L10 -> -0.01 | Q10: =IF(ABS(P10)<=0.011,"OK","CHECK") -> OK
A11: 145993502 | B11: 18-05-26 | C11: 13:51 | D11: 84902 | E11: MSZ552 | F11: Diesel | G11: Tfc Dcb Energy Hub Meer | H11: 55 | I11: 1.7488 | J11: 0.205 | K11: 1.5438 | L11: 84.91 | M11: =IF(K11<>"",K11,I11) -> 1.5438 | N11: =IF(K11="","n/a (no discount)",IF(ABS(I11-J11-K11)<=0.0001,"OK","CHECK")) -> OK | O11: =ROUND(M11*H11,2) -> 84.91 | P11: =O11-L11 -> 0 | Q11: =IF(ABS(P11)<=0.011,"OK","CHECK") -> OK
A12: 145993502 | B12: 18-05-26 | C12: 13:46 | D12: 84891 | E12: MSZ552 | F12: AdBlue | G12: Tfc Dcb Energy Hub Meer | H12: 44 | I12: 0.6 | J12: 0 | K12: 0.6 | L12: 26.4 | M12: =IF(K12<>"",K12,I12) -> 0.6 | N12: =IF(K12="","n/a (no discount)",IF(ABS(I12-J12-K12)<=0.0001,"OK","CHECK")) -> OK | O12: =ROUND(M12*H12,2) -> 26.4 | P12: =O12-L12 -> 0 | Q12: =IF(ABS(P12)<=0.011,"OK","CHECK") -> OK
A13: 168404872 | B13: 21-05-26 | C13: 13:25 | D13: 95615 | E13: AII 954 | F13: Diesel | G13: Tfc Dcb Energy Hub Meer 2 | H13: 495 | I13: 1.8116 | J13: 0.205 | K13: 1.6066 | L13: 795.27 | M13: =IF(K13<>"",K13,I13) -> 1.6066 | N13: =IF(K13="","n/a (no discount)",IF(ABS(I13-J13-K13)<=0.0001,"OK","CHECK")) -> OK | O13: =ROUND(M13*H13,2) -> 795.27 | P13: =O13-L13 -> 0 | Q13: =IF(ABS(P13)<=0.011,"OK","CHECK") -> OK
A14: 168404872 | B14: 21-05-26 | C14: 13:32 | D14: 95632 | E14: AII 954 | F14: Diesel | G14: Tfc Dcb Energy Hub Meer 2 | H14: 260.02 | I14: 1.8116 | J14: 0.205 | K14: 1.6066 | L14: 417.75 | M14: =IF(K14<>"",K14,I14) -> 1.6066 | N14: =IF(K14="","n/a (no discount)",IF(ABS(I14-J14-K14)<=0.0001,"OK","CHECK")) -> OK | O14: =ROUND(M14*H14,2) -> 417.75 | P14: =O14-L14 -> 0 | Q14: =IF(ABS(P14)<=0.011,"OK","CHECK") -> OK
A15: 168404872 | B15: 21-05-26 | C15: 13:39 | D15: 95650 | E15: AII 954 | F15: Diesel | G15: Tfc Dcb Energy Hub Meer 2 | H15: 129 | I15: 1.8116 | J15: 0.205 | K15: 1.6066 | L15: 207.26 | M15: =IF(K15<>"",K15,I15) -> 1.6066 | N15: =IF(K15="","n/a (no discount)",IF(ABS(I15-J15-K15)<=0.0001,"OK","CHECK")) -> OK | O15: =ROUND(M15*H15,2) -> 207.25 | P15: =O15-L15 -> -0.01 | Q15: =IF(ABS(P15)<=0.011,"OK","CHECK") -> OK
A16: 168404872 | B16: 21-05-26 | C16: 13:42 | D16: 95664 | E16: AII 954 | F16: AdBlue | G16: Tfc Dcb Energy Hub Meer 2 | H16: 81.02 | I16: 0.6 | J16: 0 | K16: 0.6 | L16: 48.62 | M16: =IF(K16<>"",K16,I16) -> 0.6 | N16: =IF(K16="","n/a (no discount)",IF(ABS(I16-J16-K16)<=0.0001,"OK","CHECK")) -> OK | O16: =ROUND(M16*H16,2) -> 48.61 | P16: =O16-L16 -> -0.01 | Q16: =IF(ABS(P16)<=0.011,"OK","CHECK") -> OK
A17: 280623763 | B17: 18-05-26 | C17: 08:25 | D17: 84064 | E17: NCK 230 | F17: Diesel | G17: Tfc Dcb Energy Hub Meer | H17: 602.43 | I17: 1.7488 | J17: 0.205 | K17: 1.5438 | L17: 930.04 | M17: =IF(K17<>"",K17,I17) -> 1.5438 | N17: =IF(K17="","n/a (no discount)",IF(ABS(I17-J17-K17)<=0.0001,"OK","CHECK")) -> OK | O17: =ROUND(M17*H17,2) -> 930.03 | P17: =O17-L17 -> -0.01 | Q17: =IF(ABS(P17)<=0.011,"OK","CHECK") -> OK
A18: 280623763 | B18: 18-05-26 | C18: 08:41 | D18: 84092 | E18: NCK 230 | F18: Diesel | G18: Tfc Dcb Energy Hub Meer | H18: 303.85 | I18: 1.7488 | J18: 0.205 | K18: 1.5438 | L18: 469.09 | M18: =IF(K18<>"",K18,I18) -> 1.5438 | N18: =IF(K18="","n/a (no discount)",IF(ABS(I18-J18-K18)<=0.0001,"OK","CHECK")) -> OK | O18: =ROUND(M18*H18,2) -> 469.08 | P18: =O18-L18 -> -0.01 | Q18: =IF(ABS(P18)<=0.011,"OK","CHECK") -> OK
A19: 280623763 | B19: 18-05-26 | C19: 08:45 | D19: 84104 | E19: NCK 230 | F19: Diesel | G19: Tfc Dcb Energy Hub Meer | H19: 16.77 | I19: 1.7488 | J19: 0.205 | K19: 1.5438 | L19: 25.89 | M19: =IF(K19<>"",K19,I19) -> 1.5438 | N19: =IF(K19="","n/a (no discount)",IF(ABS(I19-J19-K19)<=0.0001,"OK","CHECK")) -> OK | O19: =ROUND(M19*H19,2) -> 25.89 | P19: =O19-L19 -> 0 | Q19: =IF(ABS(P19)<=0.011,"OK","CHECK") -> OK
A20: 280623763 | B20: 22-05-26 | C20: 14:19 | D20: 98837 | E20: NCK 230 | F20: Diesel | G20: Tfc Dcb Energy Hub Meer 2 | H20: 301.16 | I20: 1.7694 | J20: 0.205 | K20: 1.5644 | L20: 471.14 | M20: =IF(K20<>"",K20,I20) -> 1.5644 | N20: =IF(K20="","n/a (no discount)",IF(ABS(I20-J20-K20)<=0.0001,"OK","CHECK")) -> OK | O20: =ROUND(M20*H20,2) -> 471.13 | P20: =O20-L20 -> -0.01 | Q20: =IF(ABS(P20)<=0.011,"OK","CHECK") -> OK
... A26: 332206574 | B26: 29-05-26 | C26: 14:28 | D26: 251689 | E26: MTZ159 | F26: Diesel | G26: Dcb Energy Hub Maasmechelen | H26: 154.53 | I26: 1.6843 | J26: 0.19 | K26: 1.4943 | L26: 230.92 | M26: =IF(K26<>"",K26,I26) -> 1.4943 | N26: =IF(K26="","n/a (no discount)",IF(ABS(I26-J26-K26)<=0.0001,"OK","CHECK")) -> OK | O26: =ROUND(M26*H26,2) -> 230.91 | P26: =O26-L26 -> -0.01 | Q26: =IF(ABS(P26)<=0.011,"OK","CHECK") -> OK
A27: 332206574 | B27: 29-05-26 | C27: 14:12 | D27: 251662 | E27: MTZ159 | F27: AdBlue | G27: Dcb Energy Hub Maasmechelen | H27: 58.93 | I27: 0.675 | L27: 39.78 | M27: =IF(K27<>"",K27,I27) -> 0.675 | N27: =IF(K27="","n/a (no discount)",IF(ABS(I27-J27-K27)<=0.0001,"OK","CHECK")) -> n/a (no discount) | O27: =ROUND(M27*H27,2) -> 39.78 | P27: =O27-L27 -> 0 | Q27: =IF(ABS(P27)<=0.011,"OK","CHECK") -> OK
A28: 368425169 | B28: 23-05-26 | C28: 03:55 | D28: 100414 | E28: MSZ543 | F28: Diesel | G28: Tfc Dcb Energy Hub Meer 2 | H28: 555 | I28: 1.7694 | J28: 0.205 | K28: 1.5644 | L28: 868.25 | M28: =IF(K28<>"",K28,I28) -> 1.5644 | N28: =IF(K28="","n/a (no discount)",IF(ABS(I28-J28-K28)<=0.0001,"OK","CHECK")) -> OK | O28: =ROUND(M28*H28,2) -> 868.24 | P28: =O28-L28 -> -0.01 | Q28: =IF(ABS(P28)<=0.011,"OK","CHECK") -> OK
A29: 368425169 | B29: 23-05-26 | C29: 04:03 | D29: 100424 | E29: MSZ543 | F29: Diesel | G29: Tfc Dcb Energy Hub Meer 2 | H29: 300 | I29: 1.7694 | J29: 0.205 | K29: 1.5644 | L29: 469.32 | M29: =IF(K29<>"",K29,I29) -> 1.5644 | N29: =IF(K29="","n/a (no discount)",IF(ABS(I29-J29-K29)<=0.0001,"OK","CHECK")) -> OK | O29: =ROUND(M29*H29,2) -> 469.32 | P29: =O29-L29 -> 0 | Q29: =IF(ABS(P29)<=0.011,"OK","CHECK") -> OK
A30: 368425169 | B30: 23-05-26 | C30: 04:13 | D30: 100438 | E30: MSZ543 | F30: Diesel | G30: Tfc Dcb Energy Hub Meer 2 | H30: 160 | I30: 1.7694 | J30: 0.205 | K30: 1.5644 | L30: 250.31 | M30: =IF(K30<>"",K30,I30) -> 1.5644 | N30: =IF(K30="","n/a (no discount)",IF(ABS(I30-J30-K30)<=0.0001,"OK","CHECK")) -> OK | O30: =ROUND(M30*H30,2) -> 250.3 | P30: =O30-L30 -> -0.01 | Q30: =IF(ABS(P30)<=0.011,"OK","CHECK") -> OK
A31: 368425169 | B31: 23-05-26 | C31: 04:08 | D31: 100431 | E31: MSZ543 | F31: AdBlue | G31: Tfc Dcb Energy Hub Meer 2 | H31: 57 | I31: 0.6 | J31: 0 | K31: 0.6 | L31: 34.2 | M31: =IF(K31<>"",K31,I31) -> 0.6 | N31: =IF(K31="","n/a (no discount)",IF(ABS(I31-J31-K31)<=0.0001,"OK","CHECK")) -> OK | O31: =ROUND(M31*H31,2) -> 34.2 | P31: =O31-L31 -> 0 | Q31: =IF(ABS(P31)<=0.011,"OK","CHECK") -> OK
A32: 390924019 | B32: 26-05-26 | C32: 12:50 | D32: 107916 | E32: NNJ 874 | F32: Diesel | G32: Tfc Dcb Energy Hub Meer 2 | H32: 580 | I32: 1.7694 | J32: 0.205 | K32: 1.5644 | L32: 907.36 | M32: =IF(K32<>"",K32,I32) -> 1.5644 | N32: =IF(K32="","n/a (no discount)",IF(ABS(I32-J32-K32)<=0.0001,"OK","CHECK")) -> OK | O32: =ROUND(M32*H32,2) -> 907.35 | P32: =O32-L32 -> -0.01 | Q32: =IF(ABS(P32)<=0.011,"OK","CHECK") -> OK
A33: 390924019 | B33: 26-05-26 | C33: 12:58 | D33: 107938 | E33: NNJ 874 | F33: Diesel | G33: Tfc Dcb Energy Hub Meer 2 | H33: 310 | I33: 1.7694 | J33: 0.205 | K33: 1.5644 | L33: 484.97 | M33: =IF(K33<>"",K33,I33) -> 1.5644 | N33: =IF(K33="","n/a (no discount)",IF(ABS(I33-J33-K33)<=0.0001,"OK","CHECK")) -> OK | O33: =ROUND(M33*H33,2) -> 484.96 | P33: =O33-L33 -> -0.01 | Q33: =IF(ABS(P33)<=0.011,"OK","CHECK") -> OK
A34: 390924019 | B34: 26-05-26 | C34: 13:03 | D34: 107952 | E34: NNJ 874 | F34: Diesel | G34: Tfc Dcb Energy Hub Meer 2 | H34: 120 | I34: 1.7694 | J34: 0.205 | K34: 1.5644 | L34: 187.73 | M34: =IF(K34<>"",K34,I34) -> 1.5644 | N34: =IF(K34="","n/a (no discount)",IF(ABS(I34-J34-K34)<=0.0001,"OK","CHECK")) -> OK | O34: =ROUND(M34*H34,2) -> 187.73 | P34: =O34-L34 -> 0 | Q34: =IF(ABS(P34)<=0.011,"OK","CHECK") -> OK
A35: 390924019 | B35: 26-05-26 | C35: 13:07 | D35: 107966 | E35: NNJ 874 | F35: AdBlue | G35: Tfc Dcb Energy Hub Meer 2 | H35: 56.71 | I35: 0.6 | J35: 0 | K35: 0.6 | L35: 34.03 | M35: =IF(K35<>"",K35,I35) -> 0.6 | N35: =IF(K35="","n/a (no discount)",IF(ABS(I35-J35-K35)<=0.0001,"OK","CHECK")) -> OK | O35: =ROUND(M35*H35,2) -> 34.03 | P35: =O35-L35 -> 0 | Q35: =IF(ABS(P35)<=0.011,"OK","CHECK") -> OK
A36: 420982795 | B36: 22-05-26 | C36: 12:39 | D36: 98533 | E36: MND 992 | F36: Diesel | G36: Tfc Dcb Energy Hub Meer | H36: 120 | I36: 1.7694 | J36: 0.205 | K36: 1.5644 | L36: 187.73 | M36: =IF(K36<>"",K36,I36) -> 1.5644 | N36: =IF(K36="","n/a (no discount)",IF(ABS(I36-J36-K36)<=0.0001,"OK","CHECK")) -> OK | O36: =ROUND(M36*H36,2) -> 187.73 | P36: =O36-L36 -> 0 | Q36: =IF(ABS(P36)<=0.011,"OK","CHECK") -> OK
A37: 420982795 | B37: 22-05-26 | C37: 12:45 | D37: 98555 | E37: MND 992 | F37: Diesel | G37: Tfc Dcb Energy Hub Meer | H37: 400 | I37: 1.7694 | J37: 0.205 | K37: 1.5644 | L37: 625.76 | M37: =IF(K37<>"",K37,I37) -> 1.5644 | N37: =IF(K37="","n/a (no discount)",IF(ABS(I37-J37-K37)<=0.0001,"OK","CHECK")) -> OK | O37: =ROUND(M37*H37,2) -> 625.76 | P37: =O37-L37 -> 0 | Q37: =IF(ABS(P37)<=0.011,"OK","CHECK") -> OK
A38: 420982795 | B38: 28-05-26 | C38: 01:03 | D38: 248135 | E38: MND 992 | F38: Diesel | G38: Romac Houdeng | H38: 205.1 | I38: 1.5944 | L38: 327.02 | M38: =IF(K38<>"",K38,I38) -> 1.5944 | N38: =IF(K38="","n/a (no discount)",IF(ABS(I38-J38-K38)<=0.0001,"OK","CHECK")) -> n/a (no discount) | O38: =ROUND(M38*H38,2) -> 327.01 | P38: =O38-L38 -> -0.01 | Q38: =IF(ABS(P38)<=0.011,"OK","CHECK") -> OK
A39: 420982795 | B39: 28-05-26 | C39: 01:08 | D39: 248142 | E39: MND 992 | F39: Diesel | G39: Romac Houdeng | H39: 340 | I39: 1.5944 | L39: 542.1 | M39: =IF(K39<>"",K39,I39) -> 1.5944 | N39: =IF(K39="","n/a (no discount)",IF(ABS(I39-J39-K39)<=0.0001,"OK","CHECK")) -> n/a (no discount) | O39: =ROUND(M39*H39,2) -> 542.1 | P39: =O39-L39 -> 0 | Q39: =IF(ABS(P39)<=0.011,"OK","CHECK") -> OK
A40: 420982795 | B40: 28-05-26 | C40: 01:14 | D40: 248149 | E40: MND 992 | F40: Diesel | G40: Romac Houdeng | H40: 550 | I40: 1.5944 | L40: 876.92 | M40: =IF(K40<>"",K40,I40) -> 1.5944 | N40: =IF(K40="","n/a (no discount)",IF(ABS(I40-J40-K40)<=0.0001,"OK","CHECK")) -> n/a (no discount) | O40: =ROUND(M40*H40,2) -> 876.92 | P40: =O40-L40 -> 0 | Q40: =IF(ABS(P40)<=0.011,"OK","CHECK") -> OK
A41: 420982795 | B41: 28-05-26 | C41: 01:21 | D41: 248157 | E41: MND 992 | F41: AdBlue | G41: Romac Houdeng | H41: 78 | I41: 0.675 | L41: 52.65 | M41: =IF(K41<>"",K41,I41) -> 0.675 | N41: =IF(K41="","n/a (no discount)",IF(ABS(I41-J41-K41)<=0.0001,"OK","CHECK")) -> n/a (no discount) | O41: =ROUND(M41*H41,2) -> 52.65 | P41: =O41-L41 -> 0 | Q41: =IF(ABS(P41)<=0.011,"OK","CHECK") -> OK
A42: 431120840 | B42: 22-05-26 | C42: 13:14 | D42: 98635 | E42: MFF 264 | F42: Diesel | G42: Tfc Dcb Energy Hub Meer | H42: 354.49 | I42: 1.7694 | J42: 0.205 | K42: 1.5644 | L42: 554.57 | M42: =IF(K42<>"",K42,I42) -> 1.5644 | N42: =IF(K42="","n/a (no discount)",IF(ABS(I42-J42-K42)<=0.0001,"OK","CHECK")) -> OK | O42: =ROUND(M42*H42,2) -> 554.56 | P42: =O42-L42 -> -0.01 | Q42: =IF(ABS(P42)<=0.011,"OK","CHECK") -> OK
A43: 431120840 | B43: 22-05-26 | C43: 13:20 | D43: 98648 | E43: MFF 264 | F43: Diesel | G43: Tfc Dcb Energy Hub Meer | H43: 384.26 | I43: 1.7694 | J43: 0.205 | K43: 1.5644 | L43: 601.14 | M43: =IF(K43<>"",K43,I43) -> 1.5644 | N43: =IF(K43="","n/a (no discount)",IF(ABS(I43-J43-K43)<=0.0001,"OK","CHECK")) -> OK | O43: =ROUND(M43*H43,2) -> 601.14 | P43: =O43-L43 -> 0 | Q43: =IF(ABS(P43)<=0.011,"OK","CHECK") -> OK
A44: 431120840 | B44: 22-05-26 | C44: 13:28 | D44: 98663 | E44: MFF 264 | F44: AdBlue | G44: Tfc Dcb Energy Hub Meer | H44: 26.75 | I44: 0.6 | J44: 0 | K44: 0.6 | L44: 16.05 | M44: =IF(K44<>"",K44,I44) -> 0.6 | N44: =IF(K44="","n/a (no discount)",IF(ABS(I44-J44-K44)<=0.0001,"OK","CHECK")) -> OK | O44: =ROUND(M44*H44,2) -> 16.05 | P44: =O44-L44 -> 0 | Q44: =IF(ABS(P44)<=0.011,"OK","CHECK") -> OK
A45: 492309405 | B45: 28-05-26 | C45: 15:46 | D45: 114524 | E45: NCK 206 | F45: Diesel | G45: Tfc Dcb Energy Hub Meer 2 | H45: 235.06 | I45: 1.7694 | J45: 0.205 | K45: 1.5644 | L45: 367.73 | M45: =IF(K45<>"",K45,I45) -> 1.5644 | N45: =IF(K45="","n/a (no discount)",IF(ABS(I45-J45-K45)<=0.0001,"OK","CHECK")) -> OK | O45: =ROUND(M45*H45,2) -> 367.73 | P45: =O45-L45 -> 0 | Q45: =IF(ABS(P45)<=0.011,"OK","CHECK") -> OK
A46: 492309405 | B46: 28-05-26 | C46: 15:51 | D46: 114532 | E46: NCK 206 | F46: Diesel | G46: Tfc Dcb Energy Hub Meer 2 | H46: 258.85 | I46: 1.7694 | J46: 0.205 | K46: 1.5644 | L46: 404.95 | M46: =IF(K46<>"",K46,I46) -> 1.5644 | N46: =IF(K46="","n/a (no discount)",IF(ABS(I46-J46-K46)<=0.0001,"OK","CHECK")) -> OK | O46: =ROUND(M46*H46,2) -> 404.94 | P46: =O46-L46 -> -0.01 | Q46: =IF(ABS(P46)<=0.011,"OK","CHECK") -> OK
A47: 492309405 | B47: 28-05-26 | C47: 15:55 | D47: 114543 | E47: NCK 206 | F47: Diesel | G47: Tfc Dcb Energy Hub Meer 2 | H47: 433.73 | I47: 1.7694 | J47: 0.205 | K47: 1.5644 | L47: 678.53 | M47: =IF(K47<>"",K47,I47) -> 1.5644 | N47: =IF(K47="","n/a (no discount)",IF(ABS(I47-J47-K47)<=0.0001,"OK","CHECK")) -> OK | O47: =ROUND(M47*H47,2) -> 678.53 | P47: =O47-L47 -> 0 | Q47: =IF(ABS(P47)<=0.011,"OK","CHECK") -> OK
A48: 492309405 | B48: 28-05-26 | C48: 16:02 | D48: 114563 | E48: NCK 206 | F48: AdBlue | G48: Tfc Dcb Energy Hub Meer 2 | H48: 48.4 | I48: 0.6 | J48: 0 | K48: 0.6 | L48: 29.04 | M48: =IF(K48<>"",K48,I48) -> 0.6 | N48: =IF(K48="","n/a (no discount)",IF(ABS(I48-J48-K48)<=0.0001,"OK","CHECK")) -> OK | O48: =ROUND(M48*H48,2) -> 29.04 | P48: =O48-L48 -> 0 | Q48: =IF(ABS(P48)<=0.011,"OK","CHECK") -> OK
A49: 496838029 | B49: 20-05-26 | C49: 15:30 | D49: 92552 | E49: MTG172 | F49: Diesel | G49: Tfc Dcb Energy Hub Meer 2 | H49: 467.67 | I49: 1.8116 | J49: 0.205 | K49: 1.6066 | L49: 751.36 | M49: =IF(K49<>"",K49,I49) -> 1.6066 | N49: =IF(K49="","n/a (no discount)",IF(ABS(I49-J49-K49)<=0.0001,"OK","CHECK")) -> OK | O49: =ROUND(M49*H49,2) -> 751.36 | P49: =O49-L49 -> 0 | Q49: =IF(ABS(P49)<=0.011,"OK","CHECK") -> OK
A50: 496838029 | B50: 20-05-26 | C50: 15:42 | D50: 92578 | E50: MTG172 | F50: Diesel | G50: Tfc Dcb Energy Hub Meer 2 | H50: 250.4 | I50: 1.8116 | J50: 0.205 | K50: 1.6066 | L50: 402.3 | M50: =IF(K50<>"",K50,I50) -> 1.6066 | N50: =IF(K50="","n/a (no discount)",IF(ABS(I50-J50-K50)<=0.0001,"OK","CHECK")) -> OK | O50: =ROUND(M50*H50,2) -> 402.29 | P50: =O50-L50 -> -0.01 | Q50: =IF(ABS(P50)<=0.011,"OK","CHECK") -> OK
A51: 496838029 | B51: 20-05-26 | C51: 15:46 | D51: 92584 | E51: MTG172 | F51: Diesel | G51: Tfc Dcb Energy Hub Meer 2 | H51: 99.57 | I51: 1.8116 | J51: 0.205 | K51: 1.6066 | L51: 159.97 | M51: =IF(K51<>"",K51,I51) -> 1.6066 | N51: =IF(K51="","n/a (no discount)",IF(ABS(I51-J51-K51)<=0.0001,"OK","CHECK")) -> OK | O51: =ROUND(M51*H51,2) -> 159.97 | P51: =O51-L51 -> 0 | Q51: =IF(ABS(P51)<=0.011,"OK","CHECK") -> OK
A52: 496838029 | B52: 30-05-26 | C52: 09:35 | D52: 119873 | E52: MTG172 | F52: Diesel | G52: Tfc Dcb Energy Hub Meer 2 | H52: 563.1 | I52: 1.6843 | J52: 0.205 | K52: 1.4793 | L52: 833 | M52: =IF(K52<>"",K52,I52) -> 1.4793 | N52: =IF(K52="","n/a (no discount)",IF(ABS(I52-J52-K52)<=0.0001,"OK","CHECK")) -> OK | O52: =ROUND(M52*H52,2) -> 832.99 | P52: =O52-L52 -> -0.01 | Q52: =IF(ABS(P52)<=0.011,"OK","CHECK") -> OK
A53: 496838029 | B53: 30-05-26 | C53: 09:47 | D53: 119911 | E53: MTG172 | F53: Diesel | G53: Tfc Dcb Energy Hub Meer 2 | H53: 288.72 | I53: 1.6843 | J53: 0.205 | K53: 1.4793 | L53: 427.11 | M53: =IF(K53<>"",K53,I53) -> 1.4793 | N53: =IF(K53="","n/a (no discount)",IF(ABS(I53-J53-K53)<=0.0001,"OK","CHECK")) -> OK | O53: =ROUND(M53*H53,2) -> 427.1 | P53: =O53-L53 -> -0.01 | Q53: =IF(ABS(P53)<=0.011,"OK","CHECK") -> OK
... A61: 647718447 | B61: 23-05-26 | C61: 15:35 | D61: 101833 | E61: NRH 225 | F61: Diesel | G61: Tfc Dcb Energy Hub Meer 2 | H61: 34.65 | I61: 1.7694 | J61: 0.205 | K61: 1.5644 | L61: 54.21 | M61: =IF(K61<>"",K61,I61) -> 1.5644 | N61: =IF(K61="","n/a (no discount)",IF(ABS(I61-J61-K61)<=0.0001,"OK","CHECK")) -> OK | O61: =ROUND(M61*H61,2) -> 54.21 | P61: =O61-L61 -> 0 | Q61: =IF(ABS(P61)<=0.011,"OK","CHECK") -> OK
A62: 649128539 | B62: 30-05-26 | C62: 06:01 | D62: 253016 | E62: MSZ557 | F62: Diesel | G62: De Warande Oostkamp | H62: 205.01 | I62: 1.5093 | L62: 309.43 | M62: =IF(K62<>"",K62,I62) -> 1.5093 | N62: =IF(K62="","n/a (no discount)",IF(ABS(I62-J62-K62)<=0.0001,"OK","CHECK")) -> n/a (no discount) | O62: =ROUND(M62*H62,2) -> 309.42 | P62: =O62-L62 -> -0.01 | Q62: =IF(ABS(P62)<=0.011,"OK","CHECK") -> OK
A63: 649128539 | B63: 30-05-26 | C63: 06:09 | D63: 253025 | E63: MSZ557 | F63: Diesel | G63: De Warande Oostkamp | H63: 430 | I63: 1.5093 | L63: 649 | M63: =IF(K63<>"",K63,I63) -> 1.5093 | N63: =IF(K63="","n/a (no discount)",IF(ABS(I63-J63-K63)<=0.0001,"OK","CHECK")) -> n/a (no discount) | O63: =ROUND(M63*H63,2) -> 649 | P63: =O63-L63 -> 0 | Q63: =IF(ABS(P63)<=0.011,"OK","CHECK") -> OK
A64: 649128539 | B64: 30-05-26 | C64: 06:16 | D64: 253033 | E64: MSZ557 | F64: AdBlue | G64: De Warande Oostkamp | H64: 44 | I64: 0.675 | L64: 29.7 | M64: =IF(K64<>"",K64,I64) -> 0.675 | N64: =IF(K64="","n/a (no discount)",IF(ABS(I64-J64-K64)<=0.0001,"OK","CHECK")) -> n/a (no discount) | O64: =ROUND(M64*H64,2) -> 29.7 | P64: =O64-L64 -> 0 | Q64: =IF(ABS(P64)<=0.011,"OK","CHECK") -> OK
A65: 707758061 | B65: 30-05-26 | C65: 07:20 | D65: 119469 | E65: MOS360 | F65: Diesel | G65: Tfc Dcb Energy Hub Meer 2 | H65: 590 | I65: 1.6843 | J65: 0.205 | K65: 1.4793 | L65: 872.79 | M65: =IF(K65<>"",K65,I65) -> 1.4793 | N65: =IF(K65="","n/a (no discount)",IF(ABS(I65-J65-K65)<=0.0001,"OK","CHECK")) -> OK | O65: =ROUND(M65*H65,2) -> 872.79 | P65: =O65-L65 -> 0 | Q65: =IF(ABS(P65)<=0.011,"OK","CHECK") -> OK
A66: 707758061 | B66: 30-05-26 | C66: 07:29 | D66: 119491 | E66: MOS360 | F66: Diesel | G66: Tfc Dcb Energy Hub Meer 2 | H66: 315.01 | I66: 1.6843 | J66: 0.205 | K66: 1.4793 | L66: 466 | M66: =IF(K66<>"",K66,I66) -> 1.4793 | N66: =IF(K66="","n/a (no discount)",IF(ABS(I66-J66-K66)<=0.0001,"OK","CHECK")) -> OK | O66: =ROUND(M66*H66,2) -> 465.99 | P66: =O66-L66 -> -0.01 | Q66: =IF(ABS(P66)<=0.011,"OK","CHECK") -> OK
A67: 707758061 | B67: 30-05-26 | C67: 07:37 | D67: 119511 | E67: MOS360 | F67: Diesel | G67: Tfc Dcb Energy Hub Meer 2 | H67: 118.01 | I67: 1.6843 | J67: 0.205 | K67: 1.4793 | L67: 174.58 | M67: =IF(K67<>"",K67,I67) -> 1.4793 | N67: =IF(K67="","n/a (no discount)",IF(ABS(I67-J67-K67)<=0.0001,"OK","CHECK")) -> OK | O67: =ROUND(M67*H67,2) -> 174.57 | P67: =O67-L67 -> -0.01 | Q67: =IF(ABS(P67)<=0.011,"OK","CHECK") -> OK
A68: 707758061 | B68: 30-05-26 | C68: 07:41 | D68: 119528 | E68: MOS360 | F68: AdBlue | G68: Tfc Dcb Energy Hub Meer 2 | H68: 78.08 | I68: 0.6 | J68: 0 | K68: 0.6 | L68: 46.85 | M68: =IF(K68<>"",K68,I68) -> 0.6 | N68: =IF(K68="","n/a (no discount)",IF(ABS(I68-J68-K68)<=0.0001,"OK","CHECK")) -> OK | O68: =ROUND(M68*H68,2) -> 46.85 | P68: =O68-L68 -> 0 | Q68: =IF(ABS(P68)<=0.011,"OK","CHECK") -> OK
A69: 771666683 | B69: 29-05-26 | C69: 16:50 | D69: 117693 | E69: AIE 819 | F69: Diesel | G69: Tfc Dcb Energy Hub Meer | H69: 528.26 | I69: 1.6843 | J69: 0.205 | K69: 1.4793 | L69: 781.46 | M69: =IF(K69<>"",K69,I69) -> 1.4793 | N69: =IF(K69="","n/a (no discount)",IF(ABS(I69-J69-K69)<=0.0001,"OK","CHECK")) -> OK | O69: =ROUND(M69*H69,2) -> 781.46 | P69: =O69-L69 -> 0 | Q69: =IF(ABS(P69)<=0.011,"OK","CHECK") -> OK
A70: 771666683 | B70: 29-05-26 | C70: 17:04 | D70: 117730 | E70: AIE 819 | F70: Diesel | G70: Tfc Dcb Energy Hub Meer | H70: 268.39 | I70: 1.6843 | J70: 0.205 | K70: 1.4793 | L70: 397.03 | M70: =IF(K70<>"",K70,I70) -> 1.4793 | N70: =IF(K70="","n/a (no discount)",IF(ABS(I70-J70-K70)<=0.0001,"OK","CHECK")) -> OK | O70: =ROUND(M70*H70,2) -> 397.03 | P70: =O70-L70 -> 0 | Q70: =IF(ABS(P70)<=0.011,"OK","CHECK") -> OK
A71: 771666683 | B71: 29-05-26 | C71: 17:09 | D71: 117745 | E71: AIE 819 | F71: Diesel | G71: Tfc Dcb Energy Hub Meer | H71: 52.45 | I71: 1.6843 | J71: 0.205 | K71: 1.4793 | L71: 77.59 | M71: =IF(K71<>"",K71,I71) -> 1.4793 | N71: =IF(K71="","n/a (no discount)",IF(ABS(I71-J71-K71)<=0.0001,"OK","CHECK")) -> OK | O71: =ROUND(M71*H71,2) -> 77.59 | P71: =O71-L71 -> 0 | Q71: =IF(ABS(P71)<=0.011,"OK","CHECK") -> OK
A72: 771666683 | B72: 29-05-26 | C72: 17:12 | D72: 117753 | E72: AIE 819 | F72: Diesel | G72: Tfc Dcb Energy Hub Meer | H72: 3.88 | I72: 1.6843 | J72: 0.205 | K72: 1.4793 | L72: 5.74 | M72: =IF(K72<>"",K72,I72) -> 1.4793 | N72: =IF(K72="","n/a (no discount)",IF(ABS(I72-J72-K72)<=0.0001,"OK","CHECK")) -> OK | O72: =ROUND(M72*H72,2) -> 5.74 | P72: =O72-L72 -> 0 | Q72: =IF(ABS(P72)<=0.011,"OK","CHECK") -> OK
A73: 771666683 | B73: 29-05-26 | C73: 16:59 | D73: 117715 | E73: AIE 819 | F73: AdBlue | G73: Tfc Dcb Energy Hub Meer | H73: 76.21 | I73: 0.6 | J73: 0 | K73: 0.6 | L73: 45.73 | M73: =IF(K73<>"",K73,I73) -> 0.6 | N73: =IF(K73="","n/a (no discount)",IF(ABS(I73-J73-K73)<=0.0001,"OK","CHECK")) -> OK | O73: =ROUND(M73*H73,2) -> 45.73 | P73: =O73-L73 -> 0 | Q73: =IF(ABS(P73)<=0.011,"OK","CHECK") -> OK
A74: 775094081 | B74: 18-05-26 | C74: 10:15 | D74: 227217 | E74: MSB265 | F74: Diesel | G74: Dcb Energy Hub Maasmechelen | H74: 625.67 | I74: 1.7488 | J74: 0.19 | K74: 1.5588 | L74: 975.3 | M74: =IF(K74<>"",K74,I74) -> 1.5588 | N74: =IF(K74="","n/a (no discount)",IF(ABS(I74-J74-K74)<=0.0001,"OK","CHECK")) -> OK | O74: =ROUND(M74*H74,2) -> 975.29 | P74: =O74-L74 -> -0.01 | Q74: =IF(ABS(P74)<=0.011,"OK","CHECK") -> OK
A75: 775094081 | B75: 18-05-26 | C75: 10:29 | D75: 227241 | E75: MSB265 | F75: Diesel | G75: Dcb Energy Hub Maasmechelen | H75: 323.08 | I75: 1.7488 | J75: 0.19 | K75: 1.5588 | L75: 503.62 | M75: =IF(K75<>"",K75,I75) -> 1.5588 | N75: =IF(K75="","n/a (no discount)",IF(ABS(I75-J75-K75)<=0.0001,"OK","CHECK")) -> OK | O75: =ROUND(M75*H75,2) -> 503.62 | P75: =O75-L75 -> 0 | Q75: =IF(ABS(P75)<=0.011,"OK","CHECK") -> OK
A76: 775094081 | B76: 18-05-26 | C76: 10:35 | D76: 227252 | E76: MSB265 | F76: Diesel | G76: Dcb Energy Hub Maasmechelen | H76: 201 | I76: 1.7488 | J76: 0.19 | K76: 1.5588 | L76: 313.32 | M76: =IF(K76<>"",K76,I76) -> 1.5588 | N76: =IF(K76="","n/a (no discount)",IF(ABS(I76-J76-K76)<=0.0001,"OK","CHECK")) -> OK | O76: =ROUND(M76*H76,2) -> 313.32 | P76: =O76-L76 -> 0 | Q76: =IF(ABS(P76)<=0.011,"OK","CHECK") -> OK
... A79: 775094081 | B79: 27-05-26 | C79: 10:36 | D79: 246671 | E79: MSB265 | F79: Diesel | G79: Dcb Energy Hub Maasmechelen | H79: 119.23 | I79: 1.7694 | J79: 0.19 | K79: 1.5794 | L79: 188.32 | M79: =IF(K79<>"",K79,I79) -> 1.5794 | N79: =IF(K79="","n/a (no discount)",IF(ABS(I79-J79-K79)<=0.0001,"OK","CHECK")) -> OK | O79: =ROUND(M79*H79,2) -> 188.31 | P79: =O79-L79 -> -0.01 | Q79: =IF(ABS(P79)<=0.011,"OK","CHECK") -> OK
A80: 775094081 | B80: 18-05-26 | C80: 10:24 | D80: 227231 | E80: MSB265 | F80: AdBlue | G80: Dcb Energy Hub Maasmechelen | H80: 45.03 | I80: 0.675 | L80: 30.4 | M80: =IF(K80<>"",K80,I80) -> 0.675 | N80: =IF(K80="","n/a (no discount)",IF(ABS(I80-J80-K80)<=0.0001,"OK","CHECK")) -> n/a (no discount) | O80: =ROUND(M80*H80,2) -> 30.4 | P80: =O80-L80 -> 0 | Q80: =IF(ABS(P80)<=0.011,"OK","CHECK") -> OK
A81: 775094081 | B81: 27-05-26 | C81: 10:40 | D81: 246679 | E81: MSB265 | F81: AdBlue | G81: Dcb Energy Hub Maasmechelen | H81: 22.45 | I81: 0.675 | L81: 15.16 | M81: =IF(K81<>"",K81,I81) -> 0.675 | N81: =IF(K81="","n/a (no discount)",IF(ABS(I81-J81-K81)<=0.0001,"OK","CHECK")) -> n/a (no discount) | O81: =ROUND(M81*H81,2) -> 15.15 | P81: =O81-L81 -> -0.01 | Q81: =IF(ABS(P81)<=0.011,"OK","CHECK") -> OK
A82: 823016623 | B82: 18-05-26 | C82: 14:57 | D82: 85096 | E82: LRN 472 | F82: Diesel | G82: Tfc Dcb Energy Hub Meer 2 | H82: 675 | I82: 1.7488 | J82: 0.205 | K82: 1.5438 | L82: 1042.07 | M82: =IF(K82<>"",K82,I82) -> 1.5438 | N82: =IF(K82="","n/a (no discount)",IF(ABS(I82-J82-K82)<=0.0001,"OK","CHECK")) -> OK | O82: =ROUND(M82*H82,2) -> 1042.07 | P82: =O82-L82 -> 0 | Q82: =IF(ABS(P82)<=0.011,"OK","CHECK") -> OK
A83: 823016623 | B83: 18-05-26 | C83: 15:07 | D83: 85127 | E83: LRN 472 | F83: Diesel | G83: Tfc Dcb Energy Hub Meer 2 | H83: 293 | I83: 1.7488 | J83: 0.205 | K83: 1.5438 | L83: 452.34 | M83: =IF(K83<>"",K83,I83) -> 1.5438 | N83: =IF(K83="","n/a (no discount)",IF(ABS(I83-J83-K83)<=0.0001,"OK","CHECK")) -> OK | O83: =ROUND(M83*H83,2) -> 452.33 | P83: =O83-L83 -> -0.01 | Q83: =IF(ABS(P83)<=0.011,"OK","CHECK") -> OK
A84: 823016623 | B84: 18-05-26 | C84: 15:12 | D84: 85146 | E84: LRN 472 | F84: Diesel | G84: Tfc Dcb Energy Hub Meer 2 | H84: 85 | I84: 1.7488 | J84: 0.205 | K84: 1.5438 | L84: 131.23 | M84: =IF(K84<>"",K84,I84) -> 1.5438 | N84: =IF(K84="","n/a (no discount)",IF(ABS(I84-J84-K84)<=0.0001,"OK","CHECK")) -> OK | O84: =ROUND(M84*H84,2) -> 131.22 | P84: =O84-L84 -> -0.01 | Q84: =IF(ABS(P84)<=0.011,"OK","CHECK") -> OK
A85: 823016623 | B85: 27-05-26 | C85: 15:28 | D85: 111452 | E85: LRN 472 | F85: Diesel | G85: Tfc Dcb Energy Hub Meer | H85: 661 | I85: 1.7694 | J85: 0.205 | K85: 1.5644 | L85: 1034.07 | M85: =IF(K85<>"",K85,I85) -> 1.5644 | N85: =IF(K85="","n/a (no discount)",IF(ABS(I85-J85-K85)<=0.0001,"OK","CHECK")) -> OK | O85: =ROUND(M85*H85,2) -> 1034.07 | P85: =O85-L85 -> 0 | Q85: =IF(ABS(P85)<=0.011,"OK","CHECK") -> OK
A86: 823016623 | B86: 27-05-26 | C86: 15:36 | D86: 111473 | E86: LRN 472 | F86: Diesel | G86: Tfc Dcb Energy Hub Meer | H86: 290 | I86: 1.7694 | J86: 0.205 | K86: 1.5644 | L86: 453.68 | M86: =IF(K86<>"",K86,I86) -> 1.5644 | N86: =IF(K86="","n/a (no discount)",IF(ABS(I86-J86-K86)<=0.0001,"OK","CHECK")) -> OK | O86: =ROUND(M86*H86,2) -> 453.68 | P86: =O86-L86 -> 0 | Q86: =IF(ABS(P86)<=0.011,"OK","CHECK") -> OK
A87: 823016623 | B87: 27-05-26 | C87: 15:42 | D87: 111486 | E87: LRN 472 | F87: Diesel | G87: Tfc Dcb Energy Hub Meer | H87: 151.01 | I87: 1.7694 | J87: 0.205 | K87: 1.5644 | L87: 236.25 | M87: =IF(K87<>"",K87,I87) -> 1.5644 | N87: =IF(K87="","n/a (no discount)",IF(ABS(I87-J87-K87)<=0.0001,"OK","CHECK")) -> OK | O87: =ROUND(M87*H87,2) -> 236.24 | P87: =O87-L87 -> -0.01 | Q87: =IF(ABS(P87)<=0.011,"OK","CHECK") -> OK
A88: 823016623 | B88: 29-05-26 | C88: 15:17 | D88: 117399 | E88: LRN 472 | F88: Diesel | G88: Tfc Dcb Energy Hub Meer | H88: 100 | I88: 1.6843 | J88: 0.205 | K88: 1.4793 | L88: 147.93 | M88: =IF(K88<>"",K88,I88) -> 1.4793 | N88: =IF(K88="","n/a (no discount)",IF(ABS(I88-J88-K88)<=0.0001,"OK","CHECK")) -> OK | O88: =ROUND(M88*H88,2) -> 147.93 | P88: =O88-L88 -> 0 | Q88: =IF(ABS(P88)<=0.011,"OK","CHECK") -> OK
A89: 823016623 | B89: 29-05-26 | C89: 15:22 | D89: 117427 | E89: LRN 472 | F89: Diesel | G89: Tfc Dcb Energy Hub Meer | H89: 52 | I89: 1.6843 | J89: 0.205 | K89: 1.4793 | L89: 76.93 | M89: =IF(K89<>"",K89,I89) -> 1.4793 | N89: =IF(K89="","n/a (no discount)",IF(ABS(I89-J89-K89)<=0.0001,"OK","CHECK")) -> OK | O89: =ROUND(M89*H89,2) -> 76.92 | P89: =O89-L89 -> -0.01 | Q89: =IF(ABS(P89)<=0.011,"OK","CHECK") -> OK
A90: 823016623 | B90: 18-05-26 | C90: 14:50 | D90: 85075 | E90: LRN 472 | F90: AdBlue | G90: Tfc Dcb Energy Hub Meer 2 | H90: 49 | I90: 0.6 | J90: 0 | K90: 0.6 | L90: 29.4 | M90: =IF(K90<>"",K90,I90) -> 0.6 | N90: =IF(K90="","n/a (no discount)",IF(ABS(I90-J90-K90)<=0.0001,"OK","CHECK")) -> OK | O90: =ROUND(M90*H90,2) -> 29.4 | P90: =O90-L90 -> 0 | Q90: =IF(ABS(P90)<=0.011,"OK","CHECK") -> OK
A91: 823016623 | B91: 27-05-26 | C91: 15:23 | D91: 111434 | E91: LRN 472 | F91: AdBlue | G91: Tfc Dcb Energy Hub Meer | H91: 48.86 | I91: 0.6 | J91: 0 | K91: 0.6 | L91: 29.32 | M91: =IF(K91<>"",K91,I91) -> 0.6 | N91: =IF(K91="","n/a (no discount)",IF(ABS(I91-J91-K91)<=0.0001,"OK","CHECK")) -> OK | O91: =ROUND(M91*H91,2) -> 29.32 | P91: =O91-L91 -> 0 | Q91: =IF(ABS(P91)<=0.011,"OK","CHECK") -> OK
A92: 823016623 | B92: 29-05-26 | C92: 15:14 | D92: 117373 | E92: LRN 472 | F92: AdBlue | G92: Tfc Dcb Energy Hub Meer | H92: 8 | I92: 0.6 | J92: 0 | K92: 0.6 | L92: 4.8 | M92: =IF(K92<>"",K92,I92) -> 0.6 | N92: =IF(K92="","n/a (no discount)",IF(ABS(I92-J92-K92)<=0.0001,"OK","CHECK")) -> OK | O92: =ROUND(M92*H92,2) -> 4.8 | P92: =O92-L92 -> 0 | Q92: =IF(ABS(P92)<=0.011,"OK","CHECK") -> OK
A93: 856166744 | B93: 26-05-26 | C93: 13:31 | D93: 108012 | E93: MFF 265 | F93: Diesel | G93: Romac Houdeng | H93: 250 | I93: 1.5944 | L93: 398.6 | M93: =IF(K93<>"",K93,I93) -> 1.5944 | N93: =IF(K93="","n/a (no discount)",IF(ABS(I93-J93-K93)<=0.0001,"OK","CHECK")) -> n/a (no discount) | O93: =ROUND(M93*H93,2) -> 398.6 | P93: =O93-L93 -> 0 | Q93: =IF(ABS(P93)<=0.011,"OK","CHECK") -> OK
A94: 856166744 | B94: 26-05-26 | C94: 13:38 | D94: 108025 | E94: MFF 265 | F94: Diesel | G94: Romac Houdeng | H94: 370 | I94: 1.5944 | L94: 589.93 | M94: =IF(K94<>"",K94,I94) -> 1.5944 | N94: =IF(K94="","n/a (no discount)",IF(ABS(I94-J94-K94)<=0.0001,"OK","CHECK")) -> n/a (no discount) | O94: =ROUND(M94*H94,2) -> 589.93 | P94: =O94-L94 -> 0 | Q94: =IF(ABS(P94)<=0.011,"OK","CHECK") -> OK
A95: 856166744 | B95: 26-05-26 | C95: 13:48 | D95: 108054 | E95: MFF 265 | F95: Diesel | G95: Romac Houdeng | H95: 45.81 | I95: 1.5944 | L95: 73.04 | M95: =IF(K95<>"",K95,I95) -> 1.5944 | N95: =IF(K95="","n/a (no discount)",IF(ABS(I95-J95-K95)<=0.0001,"OK","CHECK")) -> n/a (no discount) | O95: =ROUND(M95*H95,2) -> 73.04 | P95: =O95-L95 -> 0 | Q95: =IF(ABS(P95)<=0.011,"OK","CHECK") -> OK
A96: 856166744 | B96: 26-05-26 | C96: 13:44 | D96: 108042 | E96: MFF 265 | F96: AdBlue | G96: Romac Houdeng | H96: 19.92 | I96: 0.675 | L96: 13.45 | M96: =IF(K96<>"",K96,I96) -> 0.675 | N96: =IF(K96="","n/a (no discount)",IF(ABS(I96-J96-K96)<=0.0001,"OK","CHECK")) -> n/a (no discount) | O96: =ROUND(M96*H96,2) -> 13.45 | P96: =O96-L96 -> 0 | Q96: =IF(ABS(P96)<=0.011,"OK","CHECK") -> OK
A97: 889167685 | B97: 16-05-26 | C97: 07:11 | D97: 79582 | E97: MDU 054 | F97: Diesel | G97: Tfc Dcb Energy Hub Meer 2 | H97: 400 | I97: 1.7488 | J97: 0.205 | K97: 1.5438 | L97: 617.52 | M97: =IF(K97<>"",K97,I97) -> 1.5438 | N97: =IF(K97="","n/a (no discount)",IF(ABS(I97-J97-K97)<=0.0001,"OK","CHECK")) -> OK | O97: =ROUND(M97*H97,2) -> 617.52 | P97: =O97-L97 -> 0 | Q97: =IF(ABS(P97)<=0.011,"OK","CHECK") -> OK
A98: 889167685 | B98: 26-05-26 | C98: 15:29 | D98: 108328 | E98: MDU 054 | F98: Diesel | G98: Romac Houdeng | H98: 525 | I98: 1.5944 | L98: 837.06 | M98: =IF(K98<>"",K98,I98) -> 1.5944 | N98: =IF(K98="","n/a (no discount)",IF(ABS(I98-J98-K98)<=0.0001,"OK","CHECK")) -> n/a (no discount) | O98: =ROUND(M98*H98,2) -> 837.06 | P98: =O98-L98 -> 0 | Q98: =IF(ABS(P98)<=0.011,"OK","CHECK") -> OK
A99: 889167685 | B99: 26-05-26 | C99: 15:57 | D99: 108402 | E99: MDU 054 | F99: Diesel | G99: Romac Houdeng | H99: 179 | I99: 1.5944 | L99: 285.4 | M99: =IF(K99<>"",K99,I99) -> 1.5944 | N99: =IF(K99="","n/a (no discount)",IF(ABS(I99-J99-K99)<=0.0001,"OK","CHECK")) -> n/a (no discount) | O99: =ROUND(M99*H99,2) -> 285.4 | P99: =O99-L99 -> 0 | Q99: =IF(ABS(P99)<=0.011,"OK","CHECK") -> OK
A100: 898603163 | B100: 20-05-26 | C100: 19:49 | D100: 93346 | E100: NCK 186 | F100: Diesel | G100: Texaco Kruishoutem | H100: 632.02 | I100: 1.6366 | L100: 1034.37 | M100: =IF(K100<>"",K100,I100) -> 1.6366 | N100: =IF(K100="","n/a (no discount)",IF(ABS(I100-J100-K100)<=0.0001,"OK","CHECK")) -> n/a (no discount) | O100: =ROUND(M100*H100,2) -> 1034.36 | P100: =O100-L100 -> -0.01 | Q100: =IF(ABS(P100)<=0.011,"OK","CHECK") -> OK
A101: 898603163 | B101: 20-05-26 | C101: 20:05 | D101: 93402 | E101: NCK 186 | F101: Diesel | G101: Texaco Kruishoutem | H101: 108 | I101: 1.6366 | L101: 176.76 | M101: =IF(K101<>"",K101,I101) -> 1.6366 | N101: =IF(K101="","n/a (no discount)",IF(ABS(I101-J101-K101)<=0.0001,"OK","CHECK")) -> n/a (no discount) | O101: =ROUND(M101*H101,2) -> 176.75 | P101: =O101-L101 -> -0.01 | Q101: =IF(ABS(P101)<=0.011,"OK","CHECK") -> OK
A102: 898603163 | B102: 20-05-26 | C102: 20:01 | D102: 93388 | E102: NCK 186 | F102: AdBlue | G102: Texaco Kruishoutem | H102: 31.49 | I102: 0.675 | L102: 21.26 | M102: =IF(K102<>"",K102,I102) -> 0.675 | N102: =IF(K102="","n/a (no discount)",IF(ABS(I102-J102-K102)<=0.0001,"OK","CHECK")) -> n/a (no discount) | O102: =ROUND(M102*H102,2) -> 21.26 | P102: =O102-L102 -> 0 | Q102: =IF(ABS(P102)<=0.011,"OK","CHECK") -> OK
A103: 924148677 | B103: 20-05-26 | C103: 18:12 | D103: 93019 | E103: LPV 991 | F103: Diesel | G103: Tfc Dcb Energy Hub Meer 2 | H103: 400 | I103: 1.8116 | J103: 0.205 | K103: 1.6066 | L103: 642.64 | M103: =IF(K103<>"",K103,I103) -> 1.6066 | N103: =IF(K103="","n/a (no discount)",IF(ABS(I103-J103-K103)<=0.0001,"OK","CHECK")) -> OK | O103: =ROUND(M103*H103,2) -> 642.64 | P103: =O103-L103 -> 0 | Q103: =IF(ABS(P103)<=0.011,"OK","CHECK") -> OK
A104: 924148677 | B104: 28-05-26 | C104: 06:12 | D104: 113223 | E104: LPV 991 | F104: Diesel | G104: Tfc Dcb Energy Hub Meer | H104: 720.02 | I104: 1.7694 | J104: 0.205 | K104: 1.5644 | L104: 1126.4 | M104: =IF(K104<>"",K104,I104) -> 1.5644 | N104: =IF(K104="","n/a (no discount)",IF(ABS(I104-J104-K104)<=0.0001,"OK","CHECK")) -> OK | O104: =ROUND(M104*H104,2) -> 1126.4 | P104: =O104-L104 -> 0 | Q104: =IF(ABS(P104)<=0.011,"OK","CHECK") -> OK
A105: 924148677 | B105: 28-05-26 | C105: 06:21 | D105: 113251 | E105: LPV 991 | F105: Diesel | G105: Tfc Dcb Energy Hub Meer | H105: 150 | I105: 1.7694 | J105: 0.205 | K105: 1.5644 | L105: 234.66 | M105: =IF(K105<>"",K105,I105) -> 1.5644 | N105: =IF(K105="","n/a (no discount)",IF(ABS(I105-J105-K105)<=0.0001,"OK","CHECK")) -> OK | O105: =ROUND(M105*H105,2) -> 234.66 | P105: =O105-L105 -> 0 | Q105: =IF(ABS(P105)<=0.011,"OK","CHECK") -> OK
A106: 924148677 | B106: 28-05-26 | C106: 06:25 | D106: 113263 | E106: LPV 991 | F106: Diesel | G106: Tfc Dcb Energy Hub Meer | H106: 295.96 | I106: 1.7694 | J106: 0.205 | K106: 1.5644 | L106: 463 | M106: =IF(K106<>"",K106,I106) -> 1.5644 | N106: =IF(K106="","n/a (no discount)",IF(ABS(I106-J106-K106)<=0.0001,"OK","CHECK")) -> OK | O106: =ROUND(M106*H106,2) -> 463 | P106: =O106-L106 -> 0 | Q106: =IF(ABS(P106)<=0.011,"OK","CHECK") -> OK
A107: 936582681 | B107: 23-05-26 | C107: 07:54 | D107: 100933 | E107: LDI 991 | F107: Diesel | G107: Tfc Dcb Energy Hub Meer 2 | H107: 550.66 | I107: 1.7694 | J107: 0.205 | K107: 1.5644 | L107: 861.46 | M107: =IF(K107<>"",K107,I107) -> 1.5644 | N107: =IF(K107="","n/a (no discount)",IF(ABS(I107-J107-K107)<=0.0001,"OK","CHECK")) -> OK | O107: =ROUND(M107*H107,2) -> 861.45 | P107: =O107-L107 -> -0.01 | Q107: =IF(ABS(P107)<=0.011,"OK","CHECK") -> OK
A108: 936582681 | B108: 23-05-26 | C108: 08:01 | D108: 100956 | E108: LDI 991 | F108: Diesel | G108: Tfc Dcb Energy Hub Meer 2 | H108: 300.06 | I108: 1.7694 | J108: 0.205 | K108: 1.5644 | L108: 469.42 | M108: =IF(K108<>"",K108,I108) -> 1.5644 | N108: =IF(K108="","n/a (no discount)",IF(ABS(I108-J108-K108)<=0.0001,"OK","CHECK")) -> OK | O108: =ROUND(M108*H108,2) -> 469.41 | P108: =O108-L108 -> -0.01 | Q108: =IF(ABS(P108)<=0.011,"OK","CHECK") -> OK
A109: 936582681 | B109: 23-05-26 | C109: 08:07 | D109: 100971 | E109: LDI 991 | F109: AdBlue | G109: Tfc Dcb Energy Hub Meer 2 | H109: 49.4 | I109: 0.6 | J109: 0 | K109: 0.6 | L109: 29.64 | M109: =IF(K109<>"",K109,I109) -> 0.6 | N109: =IF(K109="","n/a (no discount)",IF(ABS(I109-J109-K109)<=0.0001,"OK","CHECK")) -> OK | O109: =ROUND(M109*H109,2) -> 29.64 | P109: =O109-L109 -> 0 | Q109: =IF(ABS(P109)<=0.011,"OK","CHECK") -> OK
A110: 952457222 | B110: 28-05-26 | C110: 13:15 | D110: 249366 | E110: NCS 504 | F110: Diesel | G110: Dcb Energy Hub Maasmechelen | H110: 543 | I110: 1.7694 | J110: 0.19 | K110: 1.5794 | L110: 857.62 | M110: =IF(K110<>"",K110,I110) -> 1.5794 | N110: =IF(K110="","n/a (no discount)",IF(ABS(I110-J110-K110)<=0.0001,"OK","CHECK")) -> OK | O110: =ROUND(M110*H110,2) -> 857.61 | P110: =O110-L110 -> -0.01 | Q110: =IF(ABS(P110)<=0.011,"OK","CHECK") -> OK
A111: 952457222 | B111: 28-05-26 | C111: 13:26 | D111: 249389 | E111: NCS 504 | F111: Diesel | G111: Dcb Energy Hub Maasmechelen | H111: 129.64 | I111: 1.7694 | J111: 0.19 | K111: 1.5794 | L111: 204.76 | M111: =IF(K111<>"",K111,I111) -> 1.5794 | N111: =IF(K111="","n/a (no discount)",IF(ABS(I111-J111-K111)<=0.0001,"OK","CHECK")) -> OK | O111: =ROUND(M111*H111,2) -> 204.75 | P111: =O111-L111 -> -0.01 | Q111: =IF(ABS(P111)<=0.011,"OK","CHECK") -> OK
A112: 952457222 | B112: 28-05-26 | C112: 13:31 | D112: 249399 | E112: NCS 504 | F112: AdBlue | G112: Dcb Energy Hub Maasmechelen | H112: 45.28 | I112: 0.675 | L112: 30.57 | M112: =IF(K112<>"",K112,I112) -> 0.675 | N112: =IF(K112="","n/a (no discount)",IF(ABS(I112-J112-K112)<=0.0001,"OK","CHECK")) -> n/a (no discount) | O112: =ROUND(M112*H112,2) -> 30.56 | P112: =O112-L112 -> -0.01 | Q112: =IF(ABS(P112)<=0.011,"OK","CHECK") -> OK
A113: 959770118 | B113: 29-05-26 | C113: 15:11 | D113: 117362 | E113: MFI170 | F113: Diesel | G113: Tfc Dcb Energy Hub Meer | H113: 567.19 | I113: 1.6843 | J113: 0.205 | K113: 1.4793 | L113: 839.05 | M113: =IF(K113<>"",K113,I113) -> 1.4793 | N113: =IF(K113="","n/a (no discount)",IF(ABS(I113-J113-K113)<=0.0001,"OK","CHECK")) -> OK | O113: =ROUND(M113*H113,2) -> 839.04 | P113: =O113-L113 -> -0.01 | Q113: =IF(ABS(P113)<=0.011,"OK","CHECK") -> OK
A114: 959770118 | B114: 29-05-26 | C114: 15:20 | D114: 117417 | E114: MFI170 | F114: Diesel | G114: Tfc Dcb Energy Hub Meer | H114: 289.94 | I114: 1.6843 | J114: 0.205 | K114: 1.4793 | L114: 428.91 | M114: =IF(K114<>"",K114,I114) -> 1.4793 | N114: =IF(K114="","n/a (no discount)",IF(ABS(I114-J114-K114)<=0.0001,"OK","CHECK")) -> OK | O114: =ROUND(M114*H114,2) -> 428.91 | P114: =O114-L114 -> 0 | Q114: =IF(ABS(P114)<=0.011,"OK","CHECK") -> OK
...

Sheet Card totals check
A1: Card | B1: Stated total EUR (net) | C1: Calc sum of lines | D1: Diff | E1: Check
A2: 108019237 | B2: 1537.81 | C2: =ROUND(SUMIF(Transactions!$A$2:$A$121,A2&"",Transactions!$L$2:$L$121),2) -> 1537.81 | D2: =C2-B2 -> 0 | E2: =IF(ABS(D2)<=0.01,"OK","CHECK") -> OK
A3: 145993502 | B3: 798.31 | C3: =ROUND(SUMIF(Transactions!$A$2:$A$121,A3&"",Transactions!$L$2:$L$121),2) -> 798.31 | D3: =C3-B3 -> 0 | E3: =IF(ABS(D3)<=0.01,"OK","CHECK") -> OK
A4: 168404872 | B4: 1468.9 | C4: =ROUND(SUMIF(Transactions!$A$2:$A$121,A4&"",Transactions!$L$2:$L$121),2) -> 1468.9 | D4: =C4-B4 -> 0 | E4: =IF(ABS(D4)<=0.01,"OK","CHECK") -> OK
A5: 280623763 | B5: 2234.29 | C5: =ROUND(SUMIF(Transactions!$A$2:$A$121,A5&"",Transactions!$L$2:$L$121),2) -> 2234.29 | D5: =C5-B5 -> 0 | E5: =IF(ABS(D5)<=0.01,"OK","CHECK") -> OK
A6: 332206574 | B6: 1197.69 | C6: =ROUND(SUMIF(Transactions!$A$2:$A$121,A6&"",Transactions!$L$2:$L$121),2) -> 1197.69 | D6: =C6-B6 -> 0 | E6: =IF(ABS(D6)<=0.01,"OK","CHECK") -> OK
A7: 368425169 | B7: 1622.08 | C7: =ROUND(SUMIF(Transactions!$A$2:$A$121,A7&"",Transactions!$L$2:$L$121),2) -> 1622.08 | D7: =C7-B7 -> 0 | E7: =IF(ABS(D7)<=0.01,"OK","CHECK") -> OK
A8: 390924019 | B8: 1614.09 | C8: =ROUND(SUMIF(Transactions!$A$2:$A$121,A8&"",Transactions!$L$2:$L$121),2) -> 1614.09 | D8: =C8-B8 -> 0 | E8: =IF(ABS(D8)<=0.01,"OK","CHECK") -> OK
A9: 420982795 | B9: 2612.18 | C9: =ROUND(SUMIF(Transactions!$A$2:$A$121,A9&"",Transactions!$L$2:$L$121),2) -> 2612.18 | D9: =C9-B9 -> 0 | E9: =IF(ABS(D9)<=0.01,"OK","CHECK") -> OK
A10: 431120840 | B10: 1171.76 | C10: =ROUND(SUMIF(Transactions!$A$2:$A$121,A10&"",Transactions!$L$2:$L$121),2) -> 1171.76 | D10: =C10-B10 -> 0 | E10: =IF(ABS(D10)<=0.01,"OK","CHECK") -> OK
A11: 492309405 | B11: 1480.25 | C11: =ROUND(SUMIF(Transactions!$A$2:$A$121,A11&"",Transactions!$L$2:$L$121),2) -> 1480.25 | D11: =C11-B11 -> 0 | E11: =IF(ABS(D11)<=0.01,"OK","CHECK") -> OK
A12: 496838029 | B12: 2915.68 | C12: =ROUND(SUMIF(Transactions!$A$2:$A$121,A12&"",Transactions!$L$2:$L$121),2) -> 2915.68 | D12: =C12-B12 -> 0 | E12: =IF(ABS(D12)<=0.01,"OK","CHECK") -> OK
A13: 575148137 | B13: 952.74 | C13: =ROUND(SUMIF(Transactions!$A$2:$A$121,A13&"",Transactions!$L$2:$L$121),2) -> 952.74 | D13: =C13-B13 -> 0 | E13: =IF(ABS(D13)<=0.01,"OK","CHECK") -> OK
... A27: 991011529 | B27: 1806.17 | C27: =ROUND(SUMIF(Transactions!$A$2:$A$121,A27&"",Transactions!$L$2:$L$121),2) -> 1806.17 | D27: =C27-B27 -> 0 | E27: =IF(ABS(D27)<=0.01,"OK","CHECK") -> OK
A28: TOTAL | B28: =SUM(B2:B27) -> 42454.54 | C28: =SUM(C2:C27) -> 42454.54 | D28: =C28-B28 -> 0 | E28: =IF(ABS(D28)<=0.01,"OK","CHECK") -> OK

Sheet Invoice totals check
A1: Check item | B1: Invoice states | C1: Calculated | D1: Diff | E1: Check
A2: Total excl. VAT EUR | B2: 42454.54 | C2: =ROUND(SUM(Transactions!$L$2:$L$121),2) -> 42454.54 | D2: =C2-B2 -> 0 | E2: =IF(ABS(D2)<=0.01,"OK","CHECK") -> OK
A3: VAT 21% EUR | B3: 8915.45 | C3: =ROUND(C2*0.21,2) -> 8915.45 | D3: =C3-B3 -> 0 | E3: =IF(ABS(D3)<=0.02,"OK","CHECK") -> OK
A4: Invoice total EUR | B4: 51369.99 | C4: =C2+C3 -> 51369.99 | D4: =C4-B4 -> 0 | E4: =IF(ABS(D4)<=0.03,"OK","CHECK") -> OK
A5: Diesel litres | B5: (not stated) | C5: =ROUND(SUMIF(Transactions!$F$2:$F$121,"Diesel",Transactions!$H$2:$H$121),2) -> 26754.06
A6: Diesel net EUR | B6: (not stated) | C6: =ROUND(SUMIF(Transactions!$F$2:$F$121,"Diesel",Transactions!$L$2:$L$121),2) -> 41568.74
A7: AdBlue litres | B7: (not stated) | C7: =ROUND(SUMIF(Transactions!$F$2:$F$121,"AdBlue",Transactions!$H$2:$H$121),2) -> 1429.3
A8: AdBlue net EUR | B8: (not stated) | C8: =ROUND(SUMIF(Transactions!$F$2:$F$121,"AdBlue",Transactions!$L$2:$L$121),2) -> 885.8

Sheet Station price analysis
A1: Station | B1: Diesel litres | C1: Diesel net EUR | D1: Avg eff. net EUR/L | E1: Discount shown?
A2: Tfc Dcb Energy Hub Meer | B2: =ROUND(SUMPRODUCT((Transactions!$G$2:$G$121=A2)*(Transactions!$F$2:$F$121="Diesel")*Transactions!$H$2:$H$121),2) -> 7397.92 | C2: =ROUND(SUMPRODUCT((Transactions!$G$2:$G$121=A2)*(Transactions!$F$2:$F$121="Diesel")*Transactions!$L$2:$L$121),2) -> 11335.75 | D2: =C2/B2 -> 1.5322888 | E2: yes (-0.2050)
A3: Tfc Dcb Energy Hub Meer 2 | B3: =ROUND(SUMPRODUCT((Transactions!$G$2:$G$121=A3)*(Transactions!$F$2:$F$121="Diesel")*Transactions!$H$2:$H$121),2) -> 11647.58 | C3: =ROUND(SUMPRODUCT((Transactions!$G$2:$G$121=A3)*(Transactions!$F$2:$F$121="Diesel")*Transactions!$L$2:$L$121),2) -> 18104.86 | D3: =C3/B3 -> 1.5543881 | E3: yes (-0.2050)
A4: Dcb Energy Hub Maasmechelen | B4: =ROUND(SUMPRODUCT((Transactions!$G$2:$G$121=A4)*(Transactions!$F$2:$F$121="Diesel")*Transactions!$H$2:$H$121),2) -> 3337.62 | C4: =ROUND(SUMPRODUCT((Transactions!$G$2:$G$121=A4)*(Transactions!$F$2:$F$121="Diesel")*Transactions!$L$2:$L$121),2) -> 5181.86 | D4: =C4/B4 -> 1.5525614 | E4: yes (-0.1900)
A5: Romac Houdeng | B5: =ROUND(SUMPRODUCT((Transactions!$G$2:$G$121=A5)*(Transactions!$F$2:$F$121="Diesel")*Transactions!$H$2:$H$121),2) -> 2995.91 | C5: =ROUND(SUMPRODUCT((Transactions!$G$2:$G$121=A5)*(Transactions!$F$2:$F$121="Diesel")*Transactions!$L$2:$L$121),2) -> 4776.71 | D5: =C5/B5 -> 1.5944104 | E5: no
A6: De Warande Oostkamp | B6: =ROUND(SUMPRODUCT((Transactions!$G$2:$G$121=A6)*(Transactions!$F$2:$F$121="Diesel")*Transactions!$H$2:$H$121),2) -> 635.01 | C6: =ROUND(SUMPRODUCT((Transactions!$G$2:$G$121=A6)*(Transactions!$F$2:$F$121="Diesel")*Transactions!$L$2:$L$121),2) -> 958.43 | D6: =C6/B6 -> 1.5093148 | E6: no
A7: Texaco Kruishoutem | B7: =ROUND(SUMPRODUCT((Transactions!$G$2:$G$121=A7)*(Transactions!$F$2:$F$121="Diesel")*Transactions!$H$2:$H$121),2) -> 740.02 | C7: =ROUND(SUMPRODUCT((Transactions!$G$2:$G$121=A7)*(Transactions!$F$2:$F$121="Diesel")*Transactions!$L$2:$L$121),2) -> 1211.13 | D7: =C7/B7 -> 1.6366179 | E7: no
A8: TOTAL | B8: =SUM(B2:B7) -> 26754.06 | C8: =SUM(C2:C7) -> 41568.74 | D8: =C8/B8 -> 1.5537358
